<?xml version="1.0" encoding="UTF-8"?>
<cesAna xmlns="http://www.xces.org/schema/2003" version="null">
   <struct type="nchunk" from="25" to="26">
      <feat name="graf:set" value="xces"/>
      <feat name="graf:id" value="n0"/>
   </struct>
   <struct type="nchunk" from="45" to="53">
      <feat name="graf:set" value="xces"/>
      <feat name="graf:id" value="n1"/>
   </struct>
   <struct type="nchunk" from="57" to="58">
      <feat name="graf:set" value="xces"/>
      <feat name="graf:id" value="n2"/>
   </struct>
   <struct type="nchunk" from="62" to="70">
      <feat name="graf:set" value="xces"/>
      <feat name="graf:id" value="n3"/>
   </struct>
   <struct type="nchunk" from="75" to="77">
      <feat name="graf:set" value="xces"/>
      <feat name="graf:id" value="n4"/>
   </struct>
   <struct type="nchunk" from="83" to="101">
      <feat name="graf:set" value="xces"/>
      <feat name="graf:id" value="n5"/>
   </struct>
   <struct type="nchunk" from="111" to="120">
      <feat name="graf:set" value="xces"/>
      <feat name="graf:id" value="n6"/>
   </struct>
   <struct type="nchunk" from="124" to="141">
      <feat name="graf:set" value="xces"/>
      <feat name="graf:id" value="n7"/>
   </struct>
   <struct type="nchunk" from="156" to="184">
      <feat name="graf:set" value="xces"/>
      <feat name="graf:id" value="n8"/>
   </struct>
   <struct type="nchunk" from="185" to="187">
      <feat name="graf:set" value="xces"/>
      <feat name="graf:id" value="n9"/>
   </struct>
   <struct type="nchunk" from="197" to="201">
      <feat name="graf:set" value="xces"/>
      <feat name="graf:id" value="n10"/>
   </struct>
   <struct type="nchunk" from="213" to="220">
      <feat name="graf:set" value="xces"/>
      <feat name="graf:id" value="n11"/>
   </struct>
   <struct type="nchunk" from="221" to="235">
      <feat name="graf:set" value="xces"/>
      <feat name="graf:id" value="n12"/>
   </struct>
   <struct type="nchunk" from="237" to="242">
      <feat name="graf:set" value="xces"/>
      <feat name="graf:id" value="n13"/>
   </struct>
   <struct type="nchunk" from="248" to="265">
      <feat name="graf:set" value="xces"/>
      <feat name="graf:id" value="n14"/>
   </struct>
   <struct type="nchunk" from="282" to="285">
      <feat name="graf:set" value="xces"/>
      <feat name="graf:id" value="n15"/>
   </struct>
   <struct type="nchunk" from="293" to="305">
      <feat name="graf:set" value="xces"/>
      <feat name="graf:id" value="n16"/>
   </struct>
   <struct type="nchunk" from="306" to="309">
      <feat name="graf:set" value="xces"/>
      <feat name="graf:id" value="n17"/>
   </struct>
   <struct type="nchunk" from="321" to="325">
      <feat name="graf:set" value="xces"/>
      <feat name="graf:id" value="n18"/>
   </struct>
   <struct type="nchunk" from="338" to="358">
      <feat name="graf:set" value="xces"/>
      <feat name="graf:id" value="n19"/>
   </struct>
   <struct type="nchunk" from="363" to="366">
      <feat name="graf:set" value="xces"/>
      <feat name="graf:id" value="n20"/>
   </struct>
   <struct type="nchunk" from="386" to="390">
      <feat name="graf:set" value="xces"/>
      <feat name="graf:id" value="n21"/>
   </struct>
   <struct type="nchunk" from="401" to="406">
      <feat name="graf:set" value="xces"/>
      <feat name="graf:id" value="n22"/>
   </struct>
   <struct type="nchunk" from="420" to="422">
      <feat name="graf:set" value="xces"/>
      <feat name="graf:id" value="n23"/>
   </struct>
   <struct type="nchunk" from="432" to="454">
      <feat name="graf:set" value="xces"/>
      <feat name="graf:id" value="n24"/>
   </struct>
   <struct type="nchunk" from="477" to="489">
      <feat name="graf:set" value="xces"/>
      <feat name="graf:id" value="n25"/>
   </struct>
   <struct type="nchunk" from="491" to="495">
      <feat name="graf:set" value="xces"/>
      <feat name="graf:id" value="n26"/>
   </struct>
   <struct type="nchunk" from="501" to="507">
      <feat name="graf:set" value="xces"/>
      <feat name="graf:id" value="n27"/>
   </struct>
   <struct type="nchunk" from="511" to="527">
      <feat name="graf:set" value="xces"/>
      <feat name="graf:id" value="n28"/>
   </struct>
   <struct type="nchunk" from="542" to="545">
      <feat name="graf:set" value="xces"/>
      <feat name="graf:id" value="n29"/>
   </struct>
   <struct type="nchunk" from="549" to="556">
      <feat name="graf:set" value="xces"/>
      <feat name="graf:id" value="n30"/>
   </struct>
   <struct type="nchunk" from="557" to="561">
      <feat name="graf:set" value="xces"/>
      <feat name="graf:id" value="n31"/>
   </struct>
   <struct type="nchunk" from="567" to="573">
      <feat name="graf:set" value="xces"/>
      <feat name="graf:id" value="n32"/>
   </struct>
   <struct type="nchunk" from="579" to="583">
      <feat name="graf:set" value="xces"/>
      <feat name="graf:id" value="n33"/>
   </struct>
   <struct type="nchunk" from="595" to="625">
      <feat name="graf:set" value="xces"/>
      <feat name="graf:id" value="n34"/>
   </struct>
   <struct type="nchunk" from="631" to="636">
      <feat name="graf:set" value="xces"/>
      <feat name="graf:id" value="n35"/>
   </struct>
   <struct type="nchunk" from="642" to="648">
      <feat name="graf:set" value="xces"/>
      <feat name="graf:id" value="n36"/>
   </struct>
   <struct type="nchunk" from="661" to="670">
      <feat name="graf:set" value="xces"/>
      <feat name="graf:id" value="n37"/>
   </struct>
   <struct type="nchunk" from="672" to="688">
      <feat name="graf:set" value="xces"/>
      <feat name="graf:id" value="n38"/>
   </struct>
   <struct type="nchunk" from="703" to="716">
      <feat name="graf:set" value="xces"/>
      <feat name="graf:id" value="n39"/>
   </struct>
   <struct type="nchunk" from="720" to="726">
      <feat name="graf:set" value="xces"/>
      <feat name="graf:id" value="n40"/>
   </struct>
   <struct type="nchunk" from="745" to="755">
      <feat name="graf:set" value="xces"/>
      <feat name="graf:id" value="n41"/>
   </struct>
   <struct type="nchunk" from="760" to="765">
      <feat name="graf:set" value="xces"/>
      <feat name="graf:id" value="n42"/>
   </struct>
   <struct type="nchunk" from="784" to="797">
      <feat name="graf:set" value="xces"/>
      <feat name="graf:id" value="n43"/>
   </struct>
   <struct type="nchunk" from="801" to="812">
      <feat name="graf:set" value="xces"/>
      <feat name="graf:id" value="n44"/>
   </struct>
   <struct type="nchunk" from="827" to="831">
      <feat name="graf:set" value="xces"/>
      <feat name="graf:id" value="n45"/>
   </struct>
   <struct type="nchunk" from="839" to="850">
      <feat name="graf:set" value="xces"/>
      <feat name="graf:id" value="n46"/>
   </struct>
   <struct type="nchunk" from="860" to="863">
      <feat name="graf:set" value="xces"/>
      <feat name="graf:id" value="n47"/>
   </struct>
   <struct type="nchunk" from="878" to="895">
      <feat name="graf:set" value="xces"/>
      <feat name="graf:id" value="n48"/>
   </struct>
   <struct type="nchunk" from="902" to="906">
      <feat name="graf:set" value="xces"/>
      <feat name="graf:id" value="n49"/>
   </struct>
   <struct type="nchunk" from="930" to="934">
      <feat name="graf:set" value="xces"/>
      <feat name="graf:id" value="n50"/>
   </struct>
   <struct type="nchunk" from="954" to="967">
      <feat name="graf:set" value="xces"/>
      <feat name="graf:id" value="n51"/>
   </struct>
   <struct type="nchunk" from="971" to="982">
      <feat name="graf:set" value="xces"/>
      <feat name="graf:id" value="n52"/>
   </struct>
   <struct type="nchunk" from="987" to="997">
      <feat name="graf:set" value="xces"/>
      <feat name="graf:id" value="n53"/>
   </struct>
   <struct type="nchunk" from="998" to="1008">
      <feat name="graf:set" value="xces"/>
      <feat name="graf:id" value="n54"/>
   </struct>
   <struct type="nchunk" from="1031" to="1041">
      <feat name="graf:set" value="xces"/>
      <feat name="graf:id" value="n55"/>
   </struct>
   <struct type="nchunk" from="1107" to="1111">
      <feat name="graf:set" value="xces"/>
      <feat name="graf:id" value="n56"/>
   </struct>
   <struct type="nchunk" from="1133" to="1137">
      <feat name="graf:set" value="xces"/>
      <feat name="graf:id" value="n57"/>
   </struct>
   <struct type="nchunk" from="1168" to="1176">
      <feat name="graf:set" value="xces"/>
      <feat name="graf:id" value="n58"/>
   </struct>
   <struct type="nchunk" from="1177" to="1178">
      <feat name="graf:set" value="xces"/>
      <feat name="graf:id" value="n59"/>
   </struct>
   <struct type="nchunk" from="1193" to="1194">
      <feat name="graf:set" value="xces"/>
      <feat name="graf:id" value="n60"/>
   </struct>
   <struct type="nchunk" from="1201" to="1203">
      <feat name="graf:set" value="xces"/>
      <feat name="graf:id" value="n61"/>
   </struct>
   <struct type="nchunk" from="1208" to="1213">
      <feat name="graf:set" value="xces"/>
      <feat name="graf:id" value="n62"/>
   </struct>
   <struct type="nchunk" from="1215" to="1225">
      <feat name="graf:set" value="xces"/>
      <feat name="graf:id" value="n63"/>
   </struct>
   <struct type="nchunk" from="1231" to="1233">
      <feat name="graf:set" value="xces"/>
      <feat name="graf:id" value="n64"/>
   </struct>
   <struct type="nchunk" from="1239" to="1243">
      <feat name="graf:set" value="xces"/>
      <feat name="graf:id" value="n65"/>
   </struct>
   <struct type="nchunk" from="1255" to="1261">
      <feat name="graf:set" value="xces"/>
      <feat name="graf:id" value="n66"/>
   </struct>
   <struct type="nchunk" from="1267" to="1272">
      <feat name="graf:set" value="xces"/>
      <feat name="graf:id" value="n67"/>
   </struct>
   <struct type="nchunk" from="1274" to="1275">
      <feat name="graf:set" value="xces"/>
      <feat name="graf:id" value="n68"/>
   </struct>
   <struct type="nchunk" from="1296" to="1310">
      <feat name="graf:set" value="xces"/>
      <feat name="graf:id" value="n69"/>
   </struct>
   <struct type="nchunk" from="1314" to="1320">
      <feat name="graf:set" value="xces"/>
      <feat name="graf:id" value="n70"/>
   </struct>
   <struct type="nchunk" from="1354" to="1365">
      <feat name="graf:set" value="xces"/>
      <feat name="graf:id" value="n71"/>
   </struct>
   <struct type="nchunk" from="1371" to="1372">
      <feat name="graf:set" value="xces"/>
      <feat name="graf:id" value="n72"/>
   </struct>
   <struct type="nchunk" from="1379" to="1383">
      <feat name="graf:set" value="xces"/>
      <feat name="graf:id" value="n73"/>
   </struct>
   <struct type="nchunk" from="1400" to="1402">
      <feat name="graf:set" value="xces"/>
      <feat name="graf:id" value="n74"/>
   </struct>
   <struct type="nchunk" from="1407" to="1427">
      <feat name="graf:set" value="xces"/>
      <feat name="graf:id" value="n75"/>
   </struct>
   <struct type="nchunk" from="1443" to="1448">
      <feat name="graf:set" value="xces"/>
      <feat name="graf:id" value="n76"/>
   </struct>
   <struct type="nchunk" from="1452" to="1472">
      <feat name="graf:set" value="xces"/>
      <feat name="graf:id" value="n77"/>
   </struct>
   <struct type="nchunk" from="1490" to="1496">
      <feat name="graf:set" value="xces"/>
      <feat name="graf:id" value="n78"/>
   </struct>
   <struct type="nchunk" from="1497" to="1502">
      <feat name="graf:set" value="xces"/>
      <feat name="graf:id" value="n79"/>
   </struct>
   <struct type="nchunk" from="1505" to="1512">
      <feat name="graf:set" value="xces"/>
      <feat name="graf:id" value="n80"/>
   </struct>
   <struct type="nchunk" from="1524" to="1529">
      <feat name="graf:set" value="xces"/>
      <feat name="graf:id" value="n81"/>
   </struct>
   <struct type="nchunk" from="1533" to="1553">
      <feat name="graf:set" value="xces"/>
      <feat name="graf:id" value="n82"/>
   </struct>
   <struct type="nchunk" from="1559" to="1562">
      <feat name="graf:set" value="xces"/>
      <feat name="graf:id" value="n83"/>
   </struct>
   <struct type="nchunk" from="1569" to="1583">
      <feat name="graf:set" value="xces"/>
      <feat name="graf:id" value="n84"/>
   </struct>
   <struct type="nchunk" from="1655" to="1659">
      <feat name="graf:set" value="xces"/>
      <feat name="graf:id" value="n85"/>
   </struct>
   <struct type="nchunk" from="1691" to="1698">
      <feat name="graf:set" value="xces"/>
      <feat name="graf:id" value="n86"/>
   </struct>
   <struct type="nchunk" from="1704" to="1708">
      <feat name="graf:set" value="xces"/>
      <feat name="graf:id" value="n87"/>
   </struct>
   <struct type="nchunk" from="1717" to="1721">
      <feat name="graf:set" value="xces"/>
      <feat name="graf:id" value="n88"/>
   </struct>
   <struct type="nchunk" from="1729" to="1739">
      <feat name="graf:set" value="xces"/>
      <feat name="graf:id" value="n89"/>
   </struct>
   <struct type="nchunk" from="1741" to="1743">
      <feat name="graf:set" value="xces"/>
      <feat name="graf:id" value="n90"/>
   </struct>
   <struct type="nchunk" from="1763" to="1765">
      <feat name="graf:set" value="xces"/>
      <feat name="graf:id" value="n91"/>
   </struct>
   <struct type="nchunk" from="1775" to="1784">
      <feat name="graf:set" value="xces"/>
      <feat name="graf:id" value="n92"/>
   </struct>
   <struct type="nchunk" from="1789" to="1791">
      <feat name="graf:set" value="xces"/>
      <feat name="graf:id" value="n93"/>
   </struct>
   <struct type="nchunk" from="1812" to="1813">
      <feat name="graf:set" value="xces"/>
      <feat name="graf:id" value="n94"/>
   </struct>
   <struct type="nchunk" from="1826" to="1828">
      <feat name="graf:set" value="xces"/>
      <feat name="graf:id" value="n95"/>
   </struct>
   <struct type="nchunk" from="1847" to="1848">
      <feat name="graf:set" value="xces"/>
      <feat name="graf:id" value="n96"/>
   </struct>
   <struct type="nchunk" from="1863" to="1875">
      <feat name="graf:set" value="xces"/>
      <feat name="graf:id" value="n97"/>
   </struct>
   <struct type="nchunk" from="1892" to="1912">
      <feat name="graf:set" value="xces"/>
      <feat name="graf:id" value="n98"/>
   </struct>
   <struct type="nchunk" from="1923" to="1924">
      <feat name="graf:set" value="xces"/>
      <feat name="graf:id" value="n99"/>
   </struct>
   <struct type="nchunk" from="1934" to="1951">
      <feat name="graf:set" value="xces"/>
      <feat name="graf:id" value="n100"/>
   </struct>
   <struct type="nchunk" from="1957" to="1959">
      <feat name="graf:set" value="xces"/>
      <feat name="graf:id" value="n101"/>
   </struct>
   <struct type="nchunk" from="1972" to="1992">
      <feat name="graf:set" value="xces"/>
      <feat name="graf:id" value="n102"/>
   </struct>
   <struct type="nchunk" from="1997" to="1998">
      <feat name="graf:set" value="xces"/>
      <feat name="graf:id" value="n103"/>
   </struct>
   <struct type="nchunk" from="2016" to="2018">
      <feat name="graf:set" value="xces"/>
      <feat name="graf:id" value="n104"/>
   </struct>
   <struct type="nchunk" from="2024" to="2031">
      <feat name="graf:set" value="xces"/>
      <feat name="graf:id" value="n105"/>
   </struct>
   <struct type="nchunk" from="2039" to="2047">
      <feat name="graf:set" value="xces"/>
      <feat name="graf:id" value="n106"/>
   </struct>
   <struct type="nchunk" from="2072" to="2074">
      <feat name="graf:set" value="xces"/>
      <feat name="graf:id" value="n107"/>
   </struct>
   <struct type="nchunk" from="2094" to="2103">
      <feat name="graf:set" value="xces"/>
      <feat name="graf:id" value="n108"/>
   </struct>
   <struct type="nchunk" from="2114" to="2116">
      <feat name="graf:set" value="xces"/>
      <feat name="graf:id" value="n109"/>
   </struct>
   <struct type="nchunk" from="2133" to="2141">
      <feat name="graf:set" value="xces"/>
      <feat name="graf:id" value="n110"/>
   </struct>
   <struct type="nchunk" from="2142" to="2146">
      <feat name="graf:set" value="xces"/>
      <feat name="graf:id" value="n111"/>
   </struct>
   <struct type="nchunk" from="2156" to="2165">
      <feat name="graf:set" value="xces"/>
      <feat name="graf:id" value="n112"/>
   </struct>
   <struct type="nchunk" from="2171" to="2172">
      <feat name="graf:set" value="xces"/>
      <feat name="graf:id" value="n113"/>
   </struct>
   <struct type="nchunk" from="2184" to="2185">
      <feat name="graf:set" value="xces"/>
      <feat name="graf:id" value="n114"/>
   </struct>
   <struct type="nchunk" from="2188" to="2201">
      <feat name="graf:set" value="xces"/>
      <feat name="graf:id" value="n115"/>
   </struct>
   <struct type="nchunk" from="2278" to="2289">
      <feat name="graf:set" value="xces"/>
      <feat name="graf:id" value="n116"/>
   </struct>
   <struct type="nchunk" from="2293" to="2299">
      <feat name="graf:set" value="xces"/>
      <feat name="graf:id" value="n117"/>
   </struct>
   <struct type="nchunk" from="2318" to="2320">
      <feat name="graf:set" value="xces"/>
      <feat name="graf:id" value="n118"/>
   </struct>
   <struct type="nchunk" from="2333" to="2342">
      <feat name="graf:set" value="xces"/>
      <feat name="graf:id" value="n119"/>
   </struct>
   <struct type="nchunk" from="2352" to="2355">
      <feat name="graf:set" value="xces"/>
      <feat name="graf:id" value="n120"/>
   </struct>
   <struct type="nchunk" from="2382" to="2392">
      <feat name="graf:set" value="xces"/>
      <feat name="graf:id" value="n121"/>
   </struct>
   <struct type="nchunk" from="2398" to="2401">
      <feat name="graf:set" value="xces"/>
      <feat name="graf:id" value="n122"/>
   </struct>
   <struct type="nchunk" from="2423" to="2428">
      <feat name="graf:set" value="xces"/>
      <feat name="graf:id" value="n123"/>
   </struct>
   <struct type="nchunk" from="2434" to="2459">
      <feat name="graf:set" value="xces"/>
      <feat name="graf:id" value="n124"/>
   </struct>
   <struct type="nchunk" from="2470" to="2471">
      <feat name="graf:set" value="xces"/>
      <feat name="graf:id" value="n125"/>
   </struct>
   <struct type="nchunk" from="2500" to="2507">
      <feat name="graf:set" value="xces"/>
      <feat name="graf:id" value="n126"/>
   </struct>
   <struct type="nchunk" from="2511" to="2520">
      <feat name="graf:set" value="xces"/>
      <feat name="graf:id" value="n127"/>
   </struct>
   <struct type="nchunk" from="2527" to="2528">
      <feat name="graf:set" value="xces"/>
      <feat name="graf:id" value="n128"/>
   </struct>
   <struct type="nchunk" from="2533" to="2543">
      <feat name="graf:set" value="xces"/>
      <feat name="graf:id" value="n129"/>
   </struct>
   <struct type="nchunk" from="2550" to="2563">
      <feat name="graf:set" value="xces"/>
      <feat name="graf:id" value="n130"/>
   </struct>
   <struct type="nchunk" from="2578" to="2580">
      <feat name="graf:set" value="xces"/>
      <feat name="graf:id" value="n131"/>
   </struct>
   <struct type="nchunk" from="2597" to="2606">
      <feat name="graf:set" value="xces"/>
      <feat name="graf:id" value="n132"/>
   </struct>
   <struct type="nchunk" from="2610" to="2614">
      <feat name="graf:set" value="xces"/>
      <feat name="graf:id" value="n133"/>
   </struct>
   <struct type="nchunk" from="2615" to="2619">
      <feat name="graf:set" value="xces"/>
      <feat name="graf:id" value="n134"/>
   </struct>
   <struct type="nchunk" from="2625" to="2629">
      <feat name="graf:set" value="xces"/>
      <feat name="graf:id" value="n135"/>
   </struct>
   <struct type="nchunk" from="2639" to="2641">
      <feat name="graf:set" value="xces"/>
      <feat name="graf:id" value="n136"/>
   </struct>
   <struct type="nchunk" from="2649" to="2653">
      <feat name="graf:set" value="xces"/>
      <feat name="graf:id" value="n137"/>
   </struct>
   <struct type="nchunk" from="2654" to="2661">
      <feat name="graf:set" value="xces"/>
      <feat name="graf:id" value="n138"/>
   </struct>
   <struct type="nchunk" from="2666" to="2668">
      <feat name="graf:set" value="xces"/>
      <feat name="graf:id" value="n139"/>
   </struct>
   <struct type="nchunk" from="2685" to="2700">
      <feat name="graf:set" value="xces"/>
      <feat name="graf:id" value="n140"/>
   </struct>
   <struct type="nchunk" from="2776" to="2779">
      <feat name="graf:set" value="xces"/>
      <feat name="graf:id" value="n141"/>
   </struct>
   <struct type="nchunk" from="2787" to="2790">
      <feat name="graf:set" value="xces"/>
      <feat name="graf:id" value="n142"/>
   </struct>
   <struct type="nchunk" from="2819" to="2820">
      <feat name="graf:set" value="xces"/>
      <feat name="graf:id" value="n143"/>
   </struct>
   <struct type="nchunk" from="2826" to="2836">
      <feat name="graf:set" value="xces"/>
      <feat name="graf:id" value="n144"/>
   </struct>
   <struct type="nchunk" from="2865" to="2883">
      <feat name="graf:set" value="xces"/>
      <feat name="graf:id" value="n145"/>
   </struct>
   <struct type="nchunk" from="2887" to="2891">
      <feat name="graf:set" value="xces"/>
      <feat name="graf:id" value="n146"/>
   </struct>
   <struct type="nchunk" from="2914" to="2932">
      <feat name="graf:set" value="xces"/>
      <feat name="graf:id" value="n147"/>
   </struct>
   <struct type="nchunk" from="2947" to="2949">
      <feat name="graf:set" value="xces"/>
      <feat name="graf:id" value="n148"/>
   </struct>
   <struct type="nchunk" from="2957" to="2961">
      <feat name="graf:set" value="xces"/>
      <feat name="graf:id" value="n149"/>
   </struct>
   <struct type="nchunk" from="2962" to="2976">
      <feat name="graf:set" value="xces"/>
      <feat name="graf:id" value="n150"/>
   </struct>
   <struct type="nchunk" from="2985" to="3003">
      <feat name="graf:set" value="xces"/>
      <feat name="graf:id" value="n151"/>
   </struct>
   <struct type="nchunk" from="3009" to="3016">
      <feat name="graf:set" value="xces"/>
      <feat name="graf:id" value="n152"/>
   </struct>
   <struct type="nchunk" from="3034" to="3039">
      <feat name="graf:set" value="xces"/>
      <feat name="graf:id" value="n153"/>
   </struct>
   <struct type="nchunk" from="3045" to="3052">
      <feat name="graf:set" value="xces"/>
      <feat name="graf:id" value="n154"/>
   </struct>
   <struct type="nchunk" from="3061" to="3065">
      <feat name="graf:set" value="xces"/>
      <feat name="graf:id" value="n155"/>
   </struct>
   <struct type="nchunk" from="3070" to="3086">
      <feat name="graf:set" value="xces"/>
      <feat name="graf:id" value="n156"/>
   </struct>
   <struct type="nchunk" from="3090" to="3100">
      <feat name="graf:set" value="xces"/>
      <feat name="graf:id" value="n157"/>
   </struct>
   <struct type="nchunk" from="3115" to="3120">
      <feat name="graf:set" value="xces"/>
      <feat name="graf:id" value="n158"/>
   </struct>
   <struct type="nchunk" from="3125" to="3141">
      <feat name="graf:set" value="xces"/>
      <feat name="graf:id" value="n159"/>
   </struct>
   <struct type="nchunk" from="3152" to="3160">
      <feat name="graf:set" value="xces"/>
      <feat name="graf:id" value="n160"/>
   </struct>
   <struct type="nchunk" from="3165" to="3167">
      <feat name="graf:set" value="xces"/>
      <feat name="graf:id" value="n161"/>
   </struct>
   <struct type="nchunk" from="3180" to="3197">
      <feat name="graf:set" value="xces"/>
      <feat name="graf:id" value="n162"/>
   </struct>
   <struct type="nchunk" from="3212" to="3215">
      <feat name="graf:set" value="xces"/>
      <feat name="graf:id" value="n163"/>
   </struct>
   <struct type="nchunk" from="3229" to="3244">
      <feat name="graf:set" value="xces"/>
      <feat name="graf:id" value="n164"/>
   </struct>
   <struct type="nchunk" from="3249" to="3265">
      <feat name="graf:set" value="xces"/>
      <feat name="graf:id" value="n165"/>
   </struct>
   <struct type="nchunk" from="3270" to="3273">
      <feat name="graf:set" value="xces"/>
      <feat name="graf:id" value="n166"/>
   </struct>
   <struct type="nchunk" from="3297" to="3308">
      <feat name="graf:set" value="xces"/>
      <feat name="graf:id" value="n167"/>
   </struct>
   <struct type="nchunk" from="3309" to="3316">
      <feat name="graf:set" value="xces"/>
      <feat name="graf:id" value="n168"/>
   </struct>
   <struct type="nchunk" from="3336" to="3350">
      <feat name="graf:set" value="xces"/>
      <feat name="graf:id" value="n169"/>
   </struct>
   <struct type="nchunk" from="3354" to="3365">
      <feat name="graf:set" value="xces"/>
      <feat name="graf:id" value="n170"/>
   </struct>
   <struct type="nchunk" from="3371" to="3373">
      <feat name="graf:set" value="xces"/>
      <feat name="graf:id" value="n171"/>
   </struct>
   <struct type="nchunk" from="3379" to="3384">
      <feat name="graf:set" value="xces"/>
      <feat name="graf:id" value="n172"/>
   </struct>
   <struct type="nchunk" from="3404" to="3413">
      <feat name="graf:set" value="xces"/>
      <feat name="graf:id" value="n173"/>
   </struct>
   <struct type="nchunk" from="3422" to="3425">
      <feat name="graf:set" value="xces"/>
      <feat name="graf:id" value="n174"/>
   </struct>
   <struct type="nchunk" from="3438" to="3446">
      <feat name="graf:set" value="xces"/>
      <feat name="graf:id" value="n175"/>
   </struct>
   <struct type="nchunk" from="3453" to="3457">
      <feat name="graf:set" value="xces"/>
      <feat name="graf:id" value="n176"/>
   </struct>
   <struct type="nchunk" from="3464" to="3467">
      <feat name="graf:set" value="xces"/>
      <feat name="graf:id" value="n177"/>
   </struct>
   <struct type="nchunk" from="3478" to="3480">
      <feat name="graf:set" value="xces"/>
      <feat name="graf:id" value="n178"/>
   </struct>
   <struct type="nchunk" from="3484" to="3493">
      <feat name="graf:set" value="xces"/>
      <feat name="graf:id" value="n179"/>
   </struct>
   <struct type="nchunk" from="3494" to="3506">
      <feat name="graf:set" value="xces"/>
      <feat name="graf:id" value="n180"/>
   </struct>
   <struct type="nchunk" from="3508" to="3513">
      <feat name="graf:set" value="xces"/>
      <feat name="graf:id" value="n181"/>
   </struct>
   <struct type="nchunk" from="3518" to="3526">
      <feat name="graf:set" value="xces"/>
      <feat name="graf:id" value="n182"/>
   </struct>
   <struct type="nchunk" from="3540" to="3557">
      <feat name="graf:set" value="xces"/>
      <feat name="graf:id" value="n183"/>
   </struct>
   <struct type="nchunk" from="3572" to="3583">
      <feat name="graf:set" value="xces"/>
      <feat name="graf:id" value="n184"/>
   </struct>
   <struct type="nchunk" from="3588" to="3594">
      <feat name="graf:set" value="xces"/>
      <feat name="graf:id" value="n185"/>
   </struct>
   <struct type="nchunk" from="3604" to="3619">
      <feat name="graf:set" value="xces"/>
      <feat name="graf:id" value="n186"/>
   </struct>
   <struct type="nchunk" from="3620" to="3624">
      <feat name="graf:set" value="xces"/>
      <feat name="graf:id" value="n187"/>
   </struct>
   <struct type="nchunk" from="3629" to="3633">
      <feat name="graf:set" value="xces"/>
      <feat name="graf:id" value="n188"/>
   </struct>
   <struct type="nchunk" from="3639" to="3647">
      <feat name="graf:set" value="xces"/>
      <feat name="graf:id" value="n189"/>
   </struct>
   <struct type="nchunk" from="3665" to="3674">
      <feat name="graf:set" value="xces"/>
      <feat name="graf:id" value="n190"/>
   </struct>
   <struct type="nchunk" from="3686" to="3690">
      <feat name="graf:set" value="xces"/>
      <feat name="graf:id" value="n191"/>
   </struct>
   <struct type="nchunk" from="3701" to="3703">
      <feat name="graf:set" value="xces"/>
      <feat name="graf:id" value="n192"/>
   </struct>
   <struct type="nchunk" from="3718" to="3728">
      <feat name="graf:set" value="xces"/>
      <feat name="graf:id" value="n193"/>
   </struct>
   <struct type="nchunk" from="3733" to="3735">
      <feat name="graf:set" value="xces"/>
      <feat name="graf:id" value="n194"/>
   </struct>
   <struct type="nchunk" from="3822" to="3836">
      <feat name="graf:set" value="xces"/>
      <feat name="graf:id" value="n195"/>
   </struct>
   <struct type="nchunk" from="3840" to="3846">
      <feat name="graf:set" value="xces"/>
      <feat name="graf:id" value="n196"/>
   </struct>
   <struct type="nchunk" from="3895" to="3897">
      <feat name="graf:set" value="xces"/>
      <feat name="graf:id" value="n197"/>
   </struct>
   <struct type="nchunk" from="3926" to="3928">
      <feat name="graf:set" value="xces"/>
      <feat name="graf:id" value="n198"/>
   </struct>
   <struct type="nchunk" from="3937" to="3952">
      <feat name="graf:set" value="xces"/>
      <feat name="graf:id" value="n199"/>
   </struct>
   <struct type="nchunk" from="3958" to="3960">
      <feat name="graf:set" value="xces"/>
      <feat name="graf:id" value="n200"/>
   </struct>
   <struct type="nchunk" from="3965" to="3968">
      <feat name="graf:set" value="xces"/>
      <feat name="graf:id" value="n201"/>
   </struct>
   <struct type="nchunk" from="3982" to="3996">
      <feat name="graf:set" value="xces"/>
      <feat name="graf:id" value="n202"/>
   </struct>
   <struct type="nchunk" from="4001" to="4013">
      <feat name="graf:set" value="xces"/>
      <feat name="graf:id" value="n203"/>
   </struct>
   <struct type="nchunk" from="4023" to="4032">
      <feat name="graf:set" value="xces"/>
      <feat name="graf:id" value="n204"/>
   </struct>
   <struct type="nchunk" from="4047" to="4051">
      <feat name="graf:set" value="xces"/>
      <feat name="graf:id" value="n205"/>
   </struct>
   <struct type="nchunk" from="4052" to="4054">
      <feat name="graf:set" value="xces"/>
      <feat name="graf:id" value="n206"/>
   </struct>
   <struct type="nchunk" from="4059" to="4061">
      <feat name="graf:set" value="xces"/>
      <feat name="graf:id" value="n207"/>
   </struct>
   <struct type="nchunk" from="4066" to="4080">
      <feat name="graf:set" value="xces"/>
      <feat name="graf:id" value="n208"/>
   </struct>
   <struct type="nchunk" from="4085" to="4098">
      <feat name="graf:set" value="xces"/>
      <feat name="graf:id" value="n209"/>
   </struct>
   <struct type="nchunk" from="4102" to="4110">
      <feat name="graf:set" value="xces"/>
      <feat name="graf:id" value="n210"/>
   </struct>
   <struct type="nchunk" from="4126" to="4130">
      <feat name="graf:set" value="xces"/>
      <feat name="graf:id" value="n211"/>
   </struct>
   <struct type="nchunk" from="4144" to="4152">
      <feat name="graf:set" value="xces"/>
      <feat name="graf:id" value="n212"/>
   </struct>
   <struct type="nchunk" from="4166" to="4170">
      <feat name="graf:set" value="xces"/>
      <feat name="graf:id" value="n213"/>
   </struct>
   <struct type="nchunk" from="4182" to="4193">
      <feat name="graf:set" value="xces"/>
      <feat name="graf:id" value="n214"/>
   </struct>
   <struct type="nchunk" from="4198" to="4200">
      <feat name="graf:set" value="xces"/>
      <feat name="graf:id" value="n215"/>
   </struct>
   <struct type="nchunk" from="4205" to="4207">
      <feat name="graf:set" value="xces"/>
      <feat name="graf:id" value="n216"/>
   </struct>
   <struct type="nchunk" from="4219" to="4223">
      <feat name="graf:set" value="xces"/>
      <feat name="graf:id" value="n217"/>
   </struct>
   <struct type="nchunk" from="4224" to="4232">
      <feat name="graf:set" value="xces"/>
      <feat name="graf:id" value="n218"/>
   </struct>
   <struct type="nchunk" from="4237" to="4239">
      <feat name="graf:set" value="xces"/>
      <feat name="graf:id" value="n219"/>
   </struct>
   <struct type="nchunk" from="4251" to="4255">
      <feat name="graf:set" value="xces"/>
      <feat name="graf:id" value="n220"/>
   </struct>
   <struct type="nchunk" from="4259" to="4276">
      <feat name="graf:set" value="xces"/>
      <feat name="graf:id" value="n221"/>
   </struct>
   <struct type="nchunk" from="4282" to="4284">
      <feat name="graf:set" value="xces"/>
      <feat name="graf:id" value="n222"/>
   </struct>
   <struct type="nchunk" from="4299" to="4303">
      <feat name="graf:set" value="xces"/>
      <feat name="graf:id" value="n223"/>
   </struct>
   <struct type="nchunk" from="4314" to="4321">
      <feat name="graf:set" value="xces"/>
      <feat name="graf:id" value="n224"/>
   </struct>
   <struct type="nchunk" from="4322" to="4323">
      <feat name="graf:set" value="xces"/>
      <feat name="graf:id" value="n225"/>
   </struct>
   <struct type="nchunk" from="4343" to="4353">
      <feat name="graf:set" value="xces"/>
      <feat name="graf:id" value="n226"/>
   </struct>
   <struct type="nchunk" from="4374" to="4375">
      <feat name="graf:set" value="xces"/>
      <feat name="graf:id" value="n227"/>
   </struct>
   <struct type="nchunk" from="4389" to="4390">
      <feat name="graf:set" value="xces"/>
      <feat name="graf:id" value="n228"/>
   </struct>
   <struct type="nchunk" from="4406" to="4424">
      <feat name="graf:set" value="xces"/>
      <feat name="graf:id" value="n229"/>
   </struct>
   <struct type="nchunk" from="4428" to="4448">
      <feat name="graf:set" value="xces"/>
      <feat name="graf:id" value="n230"/>
   </struct>
   <struct type="nchunk" from="4468" to="4469">
      <feat name="graf:set" value="xces"/>
      <feat name="graf:id" value="n231"/>
   </struct>
   <struct type="nchunk" from="4481" to="4483">
      <feat name="graf:set" value="xces"/>
      <feat name="graf:id" value="n232"/>
   </struct>
   <struct type="nchunk" from="4491" to="4506">
      <feat name="graf:set" value="xces"/>
      <feat name="graf:id" value="n233"/>
   </struct>
   <struct type="nchunk" from="4511" to="4519">
      <feat name="graf:set" value="xces"/>
      <feat name="graf:id" value="n234"/>
   </struct>
   <struct type="nchunk" from="4545" to="4552">
      <feat name="graf:set" value="xces"/>
      <feat name="graf:id" value="n235"/>
   </struct>
   <struct type="nchunk" from="4563" to="4564">
      <feat name="graf:set" value="xces"/>
      <feat name="graf:id" value="n236"/>
   </struct>
   <struct type="nchunk" from="4571" to="4580">
      <feat name="graf:set" value="xces"/>
      <feat name="graf:id" value="n237"/>
   </struct>
   <struct type="nchunk" from="4592" to="4594">
      <feat name="graf:set" value="xces"/>
      <feat name="graf:id" value="n238"/>
   </struct>
   <struct type="nchunk" from="4610" to="4613">
      <feat name="graf:set" value="xces"/>
      <feat name="graf:id" value="n239"/>
   </struct>
   <struct type="nchunk" from="4624" to="4626">
      <feat name="graf:set" value="xces"/>
      <feat name="graf:id" value="n240"/>
   </struct>
   <struct type="nchunk" from="4647" to="4652">
      <feat name="graf:set" value="xces"/>
      <feat name="graf:id" value="n241"/>
   </struct>
   <struct type="nchunk" from="4653" to="4656">
      <feat name="graf:set" value="xces"/>
      <feat name="graf:id" value="n242"/>
   </struct>
   <struct type="nchunk" from="4671" to="4705">
      <feat name="graf:set" value="xces"/>
      <feat name="graf:id" value="n243"/>
   </struct>
   <struct type="nchunk" from="4709" to="4724">
      <feat name="graf:set" value="xces"/>
      <feat name="graf:id" value="n244"/>
   </struct>
   <struct type="nchunk" from="4739" to="4743">
      <feat name="graf:set" value="xces"/>
      <feat name="graf:id" value="n245"/>
   </struct>
   <struct type="nchunk" from="4754" to="4781">
      <feat name="graf:set" value="xces"/>
      <feat name="graf:id" value="n246"/>
   </struct>
   <struct type="nchunk" from="4783" to="4786">
      <feat name="graf:set" value="xces"/>
      <feat name="graf:id" value="n247"/>
   </struct>
   <struct type="nchunk" from="4804" to="4806">
      <feat name="graf:set" value="xces"/>
      <feat name="graf:id" value="n248"/>
   </struct>
   <struct type="nchunk" from="4821" to="4823">
      <feat name="graf:set" value="xces"/>
      <feat name="graf:id" value="n249"/>
   </struct>
   <struct type="nchunk" from="4839" to="4848">
      <feat name="graf:set" value="xces"/>
      <feat name="graf:id" value="n250"/>
   </struct>
   <struct type="nchunk" from="4857" to="4866">
      <feat name="graf:set" value="xces"/>
      <feat name="graf:id" value="n251"/>
   </struct>
   <struct type="nchunk" from="4870" to="4879">
      <feat name="graf:set" value="xces"/>
      <feat name="graf:id" value="n252"/>
   </struct>
   <struct type="nchunk" from="4884" to="4886">
      <feat name="graf:set" value="xces"/>
      <feat name="graf:id" value="n253"/>
   </struct>
   <struct type="nchunk" from="4896" to="4900">
      <feat name="graf:set" value="xces"/>
      <feat name="graf:id" value="n254"/>
   </struct>
   <struct type="nchunk" from="4911" to="4916">
      <feat name="graf:set" value="xces"/>
      <feat name="graf:id" value="n255"/>
   </struct>
   <struct type="nchunk" from="4920" to="4924">
      <feat name="graf:set" value="xces"/>
      <feat name="graf:id" value="n256"/>
   </struct>
   <struct type="nchunk" from="4937" to="4940">
      <feat name="graf:set" value="xces"/>
      <feat name="graf:id" value="n257"/>
   </struct>
   <struct type="nchunk" from="4950" to="4962">
      <feat name="graf:set" value="xces"/>
      <feat name="graf:id" value="n258"/>
   </struct>
   <struct type="nchunk" from="4967" to="4969">
      <feat name="graf:set" value="xces"/>
      <feat name="graf:id" value="n259"/>
   </struct>
   <struct type="nchunk" from="4989" to="4995">
      <feat name="graf:set" value="xces"/>
      <feat name="graf:id" value="n260"/>
   </struct>
   <struct type="nchunk" from="5001" to="5006">
      <feat name="graf:set" value="xces"/>
      <feat name="graf:id" value="n261"/>
   </struct>
   <struct type="nchunk" from="5010" to="5020">
      <feat name="graf:set" value="xces"/>
      <feat name="graf:id" value="n262"/>
   </struct>
   <struct type="nchunk" from="5024" to="5033">
      <feat name="graf:set" value="xces"/>
      <feat name="graf:id" value="n263"/>
   </struct>
   <struct type="nchunk" from="5038" to="5040">
      <feat name="graf:set" value="xces"/>
      <feat name="graf:id" value="n264"/>
   </struct>
   <struct type="nchunk" from="5043" to="5059">
      <feat name="graf:set" value="xces"/>
      <feat name="graf:id" value="n265"/>
   </struct>
   <struct type="nchunk" from="5070" to="5073">
      <feat name="graf:set" value="xces"/>
      <feat name="graf:id" value="n266"/>
   </struct>
   <struct type="nchunk" from="5088" to="5098">
      <feat name="graf:set" value="xces"/>
      <feat name="graf:id" value="n267"/>
   </struct>
   <struct type="nchunk" from="5105" to="5112">
      <feat name="graf:set" value="xces"/>
      <feat name="graf:id" value="n268"/>
   </struct>
   <struct type="nchunk" from="5120" to="5122">
      <feat name="graf:set" value="xces"/>
      <feat name="graf:id" value="n269"/>
   </struct>
   <struct type="nchunk" from="5134" to="5138">
      <feat name="graf:set" value="xces"/>
      <feat name="graf:id" value="n270"/>
   </struct>
   <struct type="nchunk" from="5139" to="5150">
      <feat name="graf:set" value="xces"/>
      <feat name="graf:id" value="n271"/>
   </struct>
   <struct type="nchunk" from="5175" to="5184">
      <feat name="graf:set" value="xces"/>
      <feat name="graf:id" value="n272"/>
   </struct>
   <struct type="nchunk" from="5185" to="5186">
      <feat name="graf:set" value="xces"/>
      <feat name="graf:id" value="n273"/>
   </struct>
   <struct type="nchunk" from="5233" to="5254">
      <feat name="graf:set" value="xces"/>
      <feat name="graf:id" value="n274"/>
   </struct>
   <struct type="nchunk" from="5258" to="5265">
      <feat name="graf:set" value="xces"/>
      <feat name="graf:id" value="n275"/>
   </struct>
   <struct type="nchunk" from="5267" to="5268">
      <feat name="graf:set" value="xces"/>
      <feat name="graf:id" value="n276"/>
   </struct>
   <struct type="nchunk" from="5289" to="5308">
      <feat name="graf:set" value="xces"/>
      <feat name="graf:id" value="n277"/>
   </struct>
   <struct type="nchunk" from="5314" to="5319">
      <feat name="graf:set" value="xces"/>
      <feat name="graf:id" value="n278"/>
   </struct>
   <struct type="nchunk" from="5332" to="5336">
      <feat name="graf:set" value="xces"/>
      <feat name="graf:id" value="n279"/>
   </struct>
   <struct type="nchunk" from="5337" to="5338">
      <feat name="graf:set" value="xces"/>
      <feat name="graf:id" value="n280"/>
   </struct>
   <struct type="nchunk" from="5362" to="5376">
      <feat name="graf:set" value="xces"/>
      <feat name="graf:id" value="n281"/>
   </struct>
   <struct type="nchunk" from="5385" to="5396">
      <feat name="graf:set" value="xces"/>
      <feat name="graf:id" value="n282"/>
   </struct>
   <struct type="nchunk" from="5402" to="5405">
      <feat name="graf:set" value="xces"/>
      <feat name="graf:id" value="n283"/>
   </struct>
   <struct type="nchunk" from="5410" to="5430">
      <feat name="graf:set" value="xces"/>
      <feat name="graf:id" value="n284"/>
   </struct>
   <struct type="nchunk" from="5441" to="5443">
      <feat name="graf:set" value="xces"/>
      <feat name="graf:id" value="n285"/>
   </struct>
   <struct type="nchunk" from="5453" to="5460">
      <feat name="graf:set" value="xces"/>
      <feat name="graf:id" value="n286"/>
   </struct>
   <struct type="nchunk" from="5464" to="5469">
      <feat name="graf:set" value="xces"/>
      <feat name="graf:id" value="n287"/>
   </struct>
   <struct type="nchunk" from="5475" to="5478">
      <feat name="graf:set" value="xces"/>
      <feat name="graf:id" value="n288"/>
   </struct>
   <struct type="nchunk" from="5483" to="5491">
      <feat name="graf:set" value="xces"/>
      <feat name="graf:id" value="n289"/>
   </struct>
   <struct type="nchunk" from="5496" to="5499">
      <feat name="graf:set" value="xces"/>
      <feat name="graf:id" value="n290"/>
   </struct>
   <struct type="nchunk" from="5517" to="5523">
      <feat name="graf:set" value="xces"/>
      <feat name="graf:id" value="n291"/>
   </struct>
   <struct type="nchunk" from="5538" to="5540">
      <feat name="graf:set" value="xces"/>
      <feat name="graf:id" value="n292"/>
   </struct>
   <struct type="nchunk" from="5542" to="5544">
      <feat name="graf:set" value="xces"/>
      <feat name="graf:id" value="n293"/>
   </struct>
   <struct type="nchunk" from="5554" to="5567">
      <feat name="graf:set" value="xces"/>
      <feat name="graf:id" value="n294"/>
   </struct>
   <struct type="nchunk" from="5581" to="5585">
      <feat name="graf:set" value="xces"/>
      <feat name="graf:id" value="n295"/>
   </struct>
   <struct type="nchunk" from="5586" to="5588">
      <feat name="graf:set" value="xces"/>
      <feat name="graf:id" value="n296"/>
   </struct>
   <struct type="nchunk" from="5596" to="5608">
      <feat name="graf:set" value="xces"/>
      <feat name="graf:id" value="n297"/>
   </struct>
   <struct type="nchunk" from="5610" to="5625">
      <feat name="graf:set" value="xces"/>
      <feat name="graf:id" value="n298"/>
   </struct>
   <struct type="nchunk" from="5633" to="5636">
      <feat name="graf:set" value="xces"/>
      <feat name="graf:id" value="n299"/>
   </struct>
   <struct type="nchunk" from="5640" to="5642">
      <feat name="graf:set" value="xces"/>
      <feat name="graf:id" value="n300"/>
   </struct>
   <struct type="nchunk" from="5671" to="5673">
      <feat name="graf:set" value="xces"/>
      <feat name="graf:id" value="n301"/>
   </struct>
   <struct type="nchunk" from="5684" to="5696">
      <feat name="graf:set" value="xces"/>
      <feat name="graf:id" value="n302"/>
   </struct>
   <struct type="nchunk" from="5697" to="5699">
      <feat name="graf:set" value="xces"/>
      <feat name="graf:id" value="n303"/>
   </struct>
   <struct type="nchunk" from="5714" to="5726">
      <feat name="graf:set" value="xces"/>
      <feat name="graf:id" value="n304"/>
   </struct>
   <struct type="nchunk" from="5748" to="5750">
      <feat name="graf:set" value="xces"/>
      <feat name="graf:id" value="n305"/>
   </struct>
   <struct type="nchunk" from="5769" to="5771">
      <feat name="graf:set" value="xces"/>
      <feat name="graf:id" value="n306"/>
   </struct>
   <struct type="nchunk" from="5808" to="5810">
      <feat name="graf:set" value="xces"/>
      <feat name="graf:id" value="n307"/>
   </struct>
   <struct type="nchunk" from="5816" to="5829">
      <feat name="graf:set" value="xces"/>
      <feat name="graf:id" value="n308"/>
   </struct>
   <struct type="nchunk" from="5844" to="5846">
      <feat name="graf:set" value="xces"/>
      <feat name="graf:id" value="n309"/>
   </struct>
   <struct type="nchunk" from="5859" to="5863">
      <feat name="graf:set" value="xces"/>
      <feat name="graf:id" value="n310"/>
   </struct>
   <struct type="nchunk" from="5876" to="5878">
      <feat name="graf:set" value="xces"/>
      <feat name="graf:id" value="n311"/>
   </struct>
   <struct type="nchunk" from="5883" to="5895">
      <feat name="graf:set" value="xces"/>
      <feat name="graf:id" value="n312"/>
   </struct>
   <struct type="nchunk" from="5919" to="5921">
      <feat name="graf:set" value="xces"/>
      <feat name="graf:id" value="n313"/>
   </struct>
   <struct type="nchunk" from="5931" to="5933">
      <feat name="graf:set" value="xces"/>
      <feat name="graf:id" value="n314"/>
   </struct>
   <struct type="nchunk" from="5944" to="5946">
      <feat name="graf:set" value="xces"/>
      <feat name="graf:id" value="n315"/>
   </struct>
   <struct type="nchunk" from="5951" to="5963">
      <feat name="graf:set" value="xces"/>
      <feat name="graf:id" value="n316"/>
   </struct>
   <struct type="nchunk" from="6023" to="6028">
      <feat name="graf:set" value="xces"/>
      <feat name="graf:id" value="n317"/>
   </struct>
   <struct type="nchunk" from="6033" to="6034">
      <feat name="graf:set" value="xces"/>
      <feat name="graf:id" value="n318"/>
   </struct>
   <struct type="nchunk" from="6053" to="6063">
      <feat name="graf:set" value="xces"/>
      <feat name="graf:id" value="n319"/>
   </struct>
   <struct type="nchunk" from="6067" to="6076">
      <feat name="graf:set" value="xces"/>
      <feat name="graf:id" value="n320"/>
   </struct>
   <struct type="nchunk" from="6081" to="6083">
      <feat name="graf:set" value="xces"/>
      <feat name="graf:id" value="n321"/>
   </struct>
   <struct type="nchunk" from="6090" to="6092">
      <feat name="graf:set" value="xces"/>
      <feat name="graf:id" value="n322"/>
   </struct>
   <struct type="nchunk" from="6105" to="6106">
      <feat name="graf:set" value="xces"/>
      <feat name="graf:id" value="n323"/>
   </struct>
   <struct type="nchunk" from="6116" to="6118">
      <feat name="graf:set" value="xces"/>
      <feat name="graf:id" value="n324"/>
   </struct>
   <struct type="nchunk" from="6133" to="6143">
      <feat name="graf:set" value="xces"/>
      <feat name="graf:id" value="n325"/>
   </struct>
   <struct type="nchunk" from="6143" to="6157">
      <feat name="graf:set" value="xces"/>
      <feat name="graf:id" value="n326"/>
   </struct>
   <struct type="nchunk" from="6162" to="6172">
      <feat name="graf:set" value="xces"/>
      <feat name="graf:id" value="n327"/>
   </struct>
   <struct type="nchunk" from="6190" to="6192">
      <feat name="graf:set" value="xces"/>
      <feat name="graf:id" value="n328"/>
   </struct>
   <struct type="nchunk" from="6197" to="6199">
      <feat name="graf:set" value="xces"/>
      <feat name="graf:id" value="n329"/>
   </struct>
   <struct type="nchunk" from="6221" to="6237">
      <feat name="graf:set" value="xces"/>
      <feat name="graf:id" value="n330"/>
   </struct>
   <struct type="nchunk" from="6255" to="6266">
      <feat name="graf:set" value="xces"/>
      <feat name="graf:id" value="n331"/>
   </struct>
   <struct type="nchunk" from="6281" to="6283">
      <feat name="graf:set" value="xces"/>
      <feat name="graf:id" value="n332"/>
   </struct>
   <struct type="nchunk" from="6289" to="6294">
      <feat name="graf:set" value="xces"/>
      <feat name="graf:id" value="n333"/>
   </struct>
   <struct type="nchunk" from="6299" to="6307">
      <feat name="graf:set" value="xces"/>
      <feat name="graf:id" value="n334"/>
   </struct>
   <struct type="nchunk" from="6311" to="6326">
      <feat name="graf:set" value="xces"/>
      <feat name="graf:id" value="n335"/>
   </struct>
   <struct type="nchunk" from="6330" to="6339">
      <feat name="graf:set" value="xces"/>
      <feat name="graf:id" value="n336"/>
   </struct>
   <struct type="nchunk" from="6343" to="6351">
      <feat name="graf:set" value="xces"/>
      <feat name="graf:id" value="n337"/>
   </struct>
   <struct type="nchunk" from="6361" to="6371">
      <feat name="graf:set" value="xces"/>
      <feat name="graf:id" value="n338"/>
   </struct>
   <struct type="nchunk" from="6378" to="6379">
      <feat name="graf:set" value="xces"/>
      <feat name="graf:id" value="n339"/>
   </struct>
   <struct type="nchunk" from="6392" to="6404">
      <feat name="graf:set" value="xces"/>
      <feat name="graf:id" value="n340"/>
   </struct>
   <struct type="nchunk" from="6419" to="6421">
      <feat name="graf:set" value="xces"/>
      <feat name="graf:id" value="n341"/>
   </struct>
   <struct type="nchunk" from="6447" to="6448">
      <feat name="graf:set" value="xces"/>
      <feat name="graf:id" value="n342"/>
   </struct>
   <struct type="nchunk" from="6447" to="6447">
      <feat name="graf:set" value="xces"/>
      <feat name="graf:id" value="n343"/>
   </struct>
   <struct type="nchunk" from="6471" to="6474">
      <feat name="graf:set" value="xces"/>
      <feat name="graf:id" value="n344"/>
   </struct>
   <struct type="nchunk" from="6488" to="6490">
      <feat name="graf:set" value="xces"/>
      <feat name="graf:id" value="n345"/>
   </struct>
   <struct type="nchunk" from="6500" to="6516">
      <feat name="graf:set" value="xces"/>
      <feat name="graf:id" value="n346"/>
   </struct>
   <struct type="nchunk" from="6521" to="6523">
      <feat name="graf:set" value="xces"/>
      <feat name="graf:id" value="n347"/>
   </struct>
   <struct type="nchunk" from="6529" to="6531">
      <feat name="graf:set" value="xces"/>
      <feat name="graf:id" value="n348"/>
   </struct>
   <struct type="nchunk" from="6541" to="6542">
      <feat name="graf:set" value="xces"/>
      <feat name="graf:id" value="n349"/>
   </struct>
   <struct type="nchunk" from="6578" to="6583">
      <feat name="graf:set" value="xces"/>
      <feat name="graf:id" value="n350"/>
   </struct>
   <struct type="nchunk" from="6625" to="6628">
      <feat name="graf:set" value="xces"/>
      <feat name="graf:id" value="n351"/>
   </struct>
   <struct type="nchunk" from="6634" to="6635">
      <feat name="graf:set" value="xces"/>
      <feat name="graf:id" value="n352"/>
   </struct>
   <struct type="nchunk" from="6647" to="6649">
      <feat name="graf:set" value="xces"/>
      <feat name="graf:id" value="n353"/>
   </struct>
   <struct type="nchunk" from="6650" to="6654">
      <feat name="graf:set" value="xces"/>
      <feat name="graf:id" value="n354"/>
   </struct>
   <struct type="nchunk" from="6658" to="6666">
      <feat name="graf:set" value="xces"/>
      <feat name="graf:id" value="n355"/>
   </struct>
   <struct type="nchunk" from="6681" to="6683">
      <feat name="graf:set" value="xces"/>
      <feat name="graf:id" value="n356"/>
   </struct>
   <struct type="nchunk" from="6705" to="6723">
      <feat name="graf:set" value="xces"/>
      <feat name="graf:id" value="n357"/>
   </struct>
   <struct type="nchunk" from="6725" to="6727">
      <feat name="graf:set" value="xces"/>
      <feat name="graf:id" value="n358"/>
   </struct>
   <struct type="nchunk" from="6741" to="6777">
      <feat name="graf:set" value="xces"/>
      <feat name="graf:id" value="n359"/>
   </struct>
   <struct type="nchunk" from="6792" to="6799">
      <feat name="graf:set" value="xces"/>
      <feat name="graf:id" value="n360"/>
   </struct>
   <struct type="nchunk" from="6800" to="6802">
      <feat name="graf:set" value="xces"/>
      <feat name="graf:id" value="n361"/>
   </struct>
   <struct type="nchunk" from="6811" to="6814">
      <feat name="graf:set" value="xces"/>
      <feat name="graf:id" value="n362"/>
   </struct>
   <struct type="nchunk" from="6827" to="6829">
      <feat name="graf:set" value="xces"/>
      <feat name="graf:id" value="n363"/>
   </struct>
   <struct type="nchunk" from="6841" to="6845">
      <feat name="graf:set" value="xces"/>
      <feat name="graf:id" value="n364"/>
   </struct>
   <struct type="nchunk" from="6870" to="6872">
      <feat name="graf:set" value="xces"/>
      <feat name="graf:id" value="n365"/>
   </struct>
   <struct type="nchunk" from="6881" to="6882">
      <feat name="graf:set" value="xces"/>
      <feat name="graf:id" value="n366"/>
   </struct>
   <struct type="nchunk" from="6888" to="6893">
      <feat name="graf:set" value="xces"/>
      <feat name="graf:id" value="n367"/>
   </struct>
   <struct type="nchunk" from="6918" to="6921">
      <feat name="graf:set" value="xces"/>
      <feat name="graf:id" value="n368"/>
   </struct>
   <struct type="nchunk" from="6927" to="6943">
      <feat name="graf:set" value="xces"/>
      <feat name="graf:id" value="n369"/>
   </struct>
   <struct type="nchunk" from="6956" to="6958">
      <feat name="graf:set" value="xces"/>
      <feat name="graf:id" value="n370"/>
   </struct>
   <struct type="nchunk" from="6969" to="6972">
      <feat name="graf:set" value="xces"/>
      <feat name="graf:id" value="n371"/>
   </struct>
   <struct type="nchunk" from="7006" to="7007">
      <feat name="graf:set" value="xces"/>
      <feat name="graf:id" value="n372"/>
   </struct>
   <struct type="nchunk" from="7025" to="7027">
      <feat name="graf:set" value="xces"/>
      <feat name="graf:id" value="n373"/>
   </struct>
   <struct type="nchunk" from="7050" to="7064">
      <feat name="graf:set" value="xces"/>
      <feat name="graf:id" value="n374"/>
   </struct>
   <struct type="nchunk" from="7070" to="7072">
      <feat name="graf:set" value="xces"/>
      <feat name="graf:id" value="n375"/>
   </struct>
   <struct type="nchunk" from="7092" to="7094">
      <feat name="graf:set" value="xces"/>
      <feat name="graf:id" value="n376"/>
   </struct>
   <struct type="nchunk" from="7104" to="7107">
      <feat name="graf:set" value="xces"/>
      <feat name="graf:id" value="n377"/>
   </struct>
   <struct type="nchunk" from="7111" to="7120">
      <feat name="graf:set" value="xces"/>
      <feat name="graf:id" value="n378"/>
   </struct>
   <struct type="nchunk" from="7121" to="7124">
      <feat name="graf:set" value="xces"/>
      <feat name="graf:id" value="n379"/>
   </struct>
   <struct type="nchunk" from="7150" to="7151">
      <feat name="graf:set" value="xces"/>
      <feat name="graf:id" value="n380"/>
   </struct>
   <struct type="nchunk" from="7158" to="7174">
      <feat name="graf:set" value="xces"/>
      <feat name="graf:id" value="n381"/>
   </struct>
   <struct type="nchunk" from="7186" to="7188">
      <feat name="graf:set" value="xces"/>
      <feat name="graf:id" value="n382"/>
   </struct>
   <struct type="nchunk" from="7198" to="7200">
      <feat name="graf:set" value="xces"/>
      <feat name="graf:id" value="n383"/>
   </struct>
   <struct type="nchunk" from="7235" to="7239">
      <feat name="graf:set" value="xces"/>
      <feat name="graf:id" value="n384"/>
   </struct>
   <struct type="nchunk" from="7261" to="7268">
      <feat name="graf:set" value="xces"/>
      <feat name="graf:id" value="n385"/>
   </struct>
   <struct type="nchunk" from="7282" to="7296">
      <feat name="graf:set" value="xces"/>
      <feat name="graf:id" value="n386"/>
   </struct>
   <struct type="nchunk" from="7307" to="7311">
      <feat name="graf:set" value="xces"/>
      <feat name="graf:id" value="n387"/>
   </struct>
   <struct type="nchunk" from="7318" to="7321">
      <feat name="graf:set" value="xces"/>
      <feat name="graf:id" value="n388"/>
   </struct>
   <struct type="nchunk" from="7326" to="7329">
      <feat name="graf:set" value="xces"/>
      <feat name="graf:id" value="n389"/>
   </struct>
   <struct type="nchunk" from="7349" to="7352">
      <feat name="graf:set" value="xces"/>
      <feat name="graf:id" value="n390"/>
   </struct>
   <struct type="nchunk" from="7365" to="7373">
      <feat name="graf:set" value="xces"/>
      <feat name="graf:id" value="n391"/>
   </struct>
   <struct type="nchunk" from="7380" to="7384">
      <feat name="graf:set" value="xces"/>
      <feat name="graf:id" value="n392"/>
   </struct>
   <struct type="nchunk" from="7389" to="7390">
      <feat name="graf:set" value="xces"/>
      <feat name="graf:id" value="n393"/>
   </struct>
   <struct type="nchunk" from="7402" to="7408">
      <feat name="graf:set" value="xces"/>
      <feat name="graf:id" value="n394"/>
   </struct>
   <struct type="nchunk" from="7411" to="7414">
      <feat name="graf:set" value="xces"/>
      <feat name="graf:id" value="n395"/>
   </struct>
   <struct type="nchunk" from="7431" to="7434">
      <feat name="graf:set" value="xces"/>
      <feat name="graf:id" value="n396"/>
   </struct>
   <struct type="nchunk" from="7449" to="7451">
      <feat name="graf:set" value="xces"/>
      <feat name="graf:id" value="n397"/>
   </struct>
   <struct type="nchunk" from="7456" to="7459">
      <feat name="graf:set" value="xces"/>
      <feat name="graf:id" value="n398"/>
   </struct>
   <struct type="nchunk" from="7474" to="7477">
      <feat name="graf:set" value="xces"/>
      <feat name="graf:id" value="n399"/>
   </struct>
   <struct type="nchunk" from="7493" to="7505">
      <feat name="graf:set" value="xces"/>
      <feat name="graf:id" value="n400"/>
   </struct>
   <struct type="nchunk" from="7509" to="7517">
      <feat name="graf:set" value="xces"/>
      <feat name="graf:id" value="n401"/>
   </struct>
   <struct type="nchunk" from="7537" to="7539">
      <feat name="graf:set" value="xces"/>
      <feat name="graf:id" value="n402"/>
   </struct>
   <struct type="nchunk" from="7544" to="7563">
      <feat name="graf:set" value="xces"/>
      <feat name="graf:id" value="n403"/>
   </struct>
   <struct type="nchunk" from="7571" to="7572">
      <feat name="graf:set" value="xces"/>
      <feat name="graf:id" value="n404"/>
   </struct>
   <struct type="nchunk" from="7578" to="7580">
      <feat name="graf:set" value="xces"/>
      <feat name="graf:id" value="n405"/>
   </struct>
   <struct type="nchunk" from="7588" to="7600">
      <feat name="graf:set" value="xces"/>
      <feat name="graf:id" value="n406"/>
   </struct>
   <struct type="nchunk" from="7605" to="7618">
      <feat name="graf:set" value="xces"/>
      <feat name="graf:id" value="n407"/>
   </struct>
   <struct type="nchunk" from="7633" to="7642">
      <feat name="graf:set" value="xces"/>
      <feat name="graf:id" value="n408"/>
   </struct>
   <struct type="nchunk" from="7647" to="7648">
      <feat name="graf:set" value="xces"/>
      <feat name="graf:id" value="n409"/>
   </struct>
   <struct type="nchunk" from="7674" to="7678">
      <feat name="graf:set" value="xces"/>
      <feat name="graf:id" value="n410"/>
   </struct>
   <struct type="nchunk" from="7688" to="7695">
      <feat name="graf:set" value="xces"/>
      <feat name="graf:id" value="n411"/>
   </struct>
   <struct type="nchunk" from="7709" to="7710">
      <feat name="graf:set" value="xces"/>
      <feat name="graf:id" value="n412"/>
   </struct>
   <struct type="nchunk" from="7721" to="7735">
      <feat name="graf:set" value="xces"/>
      <feat name="graf:id" value="n413"/>
   </struct>
   <struct type="nchunk" from="7741" to="7743">
      <feat name="graf:set" value="xces"/>
      <feat name="graf:id" value="n414"/>
   </struct>
   <struct type="nchunk" from="7757" to="7767">
      <feat name="graf:set" value="xces"/>
      <feat name="graf:id" value="n415"/>
   </struct>
   <struct type="nchunk" from="7775" to="7777">
      <feat name="graf:set" value="xces"/>
      <feat name="graf:id" value="n416"/>
   </struct>
   <struct type="nchunk" from="7790" to="7803">
      <feat name="graf:set" value="xces"/>
      <feat name="graf:id" value="n417"/>
   </struct>
   <struct type="nchunk" from="7812" to="7821">
      <feat name="graf:set" value="xces"/>
      <feat name="graf:id" value="n418"/>
   </struct>
   <struct type="nchunk" from="7823" to="7824">
      <feat name="graf:set" value="xces"/>
      <feat name="graf:id" value="n419"/>
   </struct>
   <struct type="nchunk" from="7845" to="7854">
      <feat name="graf:set" value="xces"/>
      <feat name="graf:id" value="n420"/>
   </struct>
   <struct type="nchunk" from="7855" to="7864">
      <feat name="graf:set" value="xces"/>
      <feat name="graf:id" value="n421"/>
   </struct>
   <struct type="nchunk" from="7889" to="7891">
      <feat name="graf:set" value="xces"/>
      <feat name="graf:id" value="n422"/>
   </struct>
   <struct type="nchunk" from="7913" to="7923">
      <feat name="graf:set" value="xces"/>
      <feat name="graf:id" value="n423"/>
   </struct>
   <struct type="nchunk" from="7925" to="7928">
      <feat name="graf:set" value="xces"/>
      <feat name="graf:id" value="n424"/>
   </struct>
   <struct type="nchunk" from="7940" to="7950">
      <feat name="graf:set" value="xces"/>
      <feat name="graf:id" value="n425"/>
   </struct>
   <struct type="nchunk" from="7955" to="7958">
      <feat name="graf:set" value="xces"/>
      <feat name="graf:id" value="n426"/>
   </struct>
   <struct type="nchunk" from="7970" to="7977">
      <feat name="graf:set" value="xces"/>
      <feat name="graf:id" value="n427"/>
   </struct>
   <struct type="nchunk" from="7992" to="7999">
      <feat name="graf:set" value="xces"/>
      <feat name="graf:id" value="n428"/>
   </struct>
   <struct type="nchunk" from="8004" to="8015">
      <feat name="graf:set" value="xces"/>
      <feat name="graf:id" value="n429"/>
   </struct>
   <struct type="nchunk" from="8026" to="8040">
      <feat name="graf:set" value="xces"/>
      <feat name="graf:id" value="n430"/>
   </struct>
   <struct type="nchunk" from="8044" to="8055">
      <feat name="graf:set" value="xces"/>
      <feat name="graf:id" value="n431"/>
   </struct>
   <struct type="nchunk" from="8074" to="8075">
      <feat name="graf:set" value="xces"/>
      <feat name="graf:id" value="n432"/>
   </struct>
   <struct type="nchunk" from="8091" to="8093">
      <feat name="graf:set" value="xces"/>
      <feat name="graf:id" value="n433"/>
   </struct>
   <struct type="nchunk" from="8105" to="8116">
      <feat name="graf:set" value="xces"/>
      <feat name="graf:id" value="n434"/>
   </struct>
   <struct type="nchunk" from="8134" to="8141">
      <feat name="graf:set" value="xces"/>
      <feat name="graf:id" value="n435"/>
   </struct>
   <struct type="nchunk" from="8142" to="8143">
      <feat name="graf:set" value="xces"/>
      <feat name="graf:id" value="n436"/>
   </struct>
   <struct type="nchunk" from="8176" to="8188">
      <feat name="graf:set" value="xces"/>
      <feat name="graf:id" value="n437"/>
   </struct>
   <struct type="nchunk" from="8203" to="8205">
      <feat name="graf:set" value="xces"/>
      <feat name="graf:id" value="n438"/>
   </struct>
   <struct type="nchunk" from="8223" to="8239">
      <feat name="graf:set" value="xces"/>
      <feat name="graf:id" value="n439"/>
   </struct>
   <struct type="nchunk" from="8244" to="8248">
      <feat name="graf:set" value="xces"/>
      <feat name="graf:id" value="n440"/>
   </struct>
   <struct type="nchunk" from="8255" to="8272">
      <feat name="graf:set" value="xces"/>
      <feat name="graf:id" value="n441"/>
   </struct>
   <struct type="nchunk" from="8278" to="8295">
      <feat name="graf:set" value="xces"/>
      <feat name="graf:id" value="n442"/>
   </struct>
   <struct type="nchunk" from="8305" to="8314">
      <feat name="graf:set" value="xces"/>
      <feat name="graf:id" value="n443"/>
   </struct>
   <struct type="nchunk" from="8318" to="8320">
      <feat name="graf:set" value="xces"/>
      <feat name="graf:id" value="n444"/>
   </struct>
   <struct type="nchunk" from="8325" to="8330">
      <feat name="graf:set" value="xces"/>
      <feat name="graf:id" value="n445"/>
   </struct>
   <struct type="nchunk" from="8334" to="8348">
      <feat name="graf:set" value="xces"/>
      <feat name="graf:id" value="n446"/>
   </struct>
   <struct type="nchunk" from="8356" to="8371">
      <feat name="graf:set" value="xces"/>
      <feat name="graf:id" value="n447"/>
   </struct>
   <struct type="nchunk" from="8386" to="8388">
      <feat name="graf:set" value="xces"/>
      <feat name="graf:id" value="n448"/>
   </struct>
   <struct type="nchunk" from="8393" to="8411">
      <feat name="graf:set" value="xces"/>
      <feat name="graf:id" value="n449"/>
   </struct>
   <struct type="nchunk" from="8427" to="8429">
      <feat name="graf:set" value="xces"/>
      <feat name="graf:id" value="n450"/>
   </struct>
   <struct type="nchunk" from="8448" to="8457">
      <feat name="graf:set" value="xces"/>
      <feat name="graf:id" value="n451"/>
   </struct>
   <struct type="nchunk" from="8465" to="8478">
      <feat name="graf:set" value="xces"/>
      <feat name="graf:id" value="n452"/>
   </struct>
   <struct type="nchunk" from="8483" to="8485">
      <feat name="graf:set" value="xces"/>
      <feat name="graf:id" value="n453"/>
   </struct>
   <struct type="nchunk" from="8497" to="8502">
      <feat name="graf:set" value="xces"/>
      <feat name="graf:id" value="n454"/>
   </struct>
   <struct type="nchunk" from="8503" to="8513">
      <feat name="graf:set" value="xces"/>
      <feat name="graf:id" value="n455"/>
   </struct>
   <struct type="nchunk" from="8522" to="8524">
      <feat name="graf:set" value="xces"/>
      <feat name="graf:id" value="n456"/>
   </struct>
   <struct type="nchunk" from="8534" to="8542">
      <feat name="graf:set" value="xces"/>
      <feat name="graf:id" value="n457"/>
   </struct>
   <struct type="nchunk" from="8552" to="8563">
      <feat name="graf:set" value="xces"/>
      <feat name="graf:id" value="n458"/>
   </struct>
   <struct type="nchunk" from="8569" to="8571">
      <feat name="graf:set" value="xces"/>
      <feat name="graf:id" value="n459"/>
   </struct>
   <struct type="nchunk" from="8595" to="8597">
      <feat name="graf:set" value="xces"/>
      <feat name="graf:id" value="n460"/>
   </struct>
   <struct type="nchunk" from="8619" to="8629">
      <feat name="graf:set" value="xces"/>
      <feat name="graf:id" value="n461"/>
   </struct>
   <struct type="nchunk" from="8633" to="8646">
      <feat name="graf:set" value="xces"/>
      <feat name="graf:id" value="n462"/>
   </struct>
   <struct type="nchunk" from="8647" to="8649">
      <feat name="graf:set" value="xces"/>
      <feat name="graf:id" value="n463"/>
   </struct>
   <struct type="nchunk" from="8662" to="8663">
      <feat name="graf:set" value="xces"/>
      <feat name="graf:id" value="n464"/>
   </struct>
   <struct type="nchunk" from="8676" to="8677">
      <feat name="graf:set" value="xces"/>
      <feat name="graf:id" value="n465"/>
   </struct>
   <struct type="nchunk" from="8684" to="8686">
      <feat name="graf:set" value="xces"/>
      <feat name="graf:id" value="n466"/>
   </struct>
   <struct type="nchunk" from="8691" to="8702">
      <feat name="graf:set" value="xces"/>
      <feat name="graf:id" value="n467"/>
   </struct>
   <struct type="nchunk" from="8708" to="8710">
      <feat name="graf:set" value="xces"/>
      <feat name="graf:id" value="n468"/>
   </struct>
   <struct type="nchunk" from="8715" to="8732">
      <feat name="graf:set" value="xces"/>
      <feat name="graf:id" value="n469"/>
   </struct>
   <struct type="nchunk" from="8745" to="8761">
      <feat name="graf:set" value="xces"/>
      <feat name="graf:id" value="n470"/>
   </struct>
   <struct type="nchunk" from="8776" to="8778">
      <feat name="graf:set" value="xces"/>
      <feat name="graf:id" value="n471"/>
   </struct>
   <struct type="nchunk" from="8783" to="8809">
      <feat name="graf:set" value="xces"/>
      <feat name="graf:id" value="n472"/>
   </struct>
   <struct type="nchunk" from="8827" to="8835">
      <feat name="graf:set" value="xces"/>
      <feat name="graf:id" value="n473"/>
   </struct>
   <struct type="nchunk" from="8840" to="8844">
      <feat name="graf:set" value="xces"/>
      <feat name="graf:id" value="n474"/>
   </struct>
   <struct type="nchunk" from="8850" to="8869">
      <feat name="graf:set" value="xces"/>
      <feat name="graf:id" value="n475"/>
   </struct>
   <struct type="nchunk" from="8879" to="8914">
      <feat name="graf:set" value="xces"/>
      <feat name="graf:id" value="n476"/>
   </struct>
   <struct type="nchunk" from="8915" to="8917">
      <feat name="graf:set" value="xces"/>
      <feat name="graf:id" value="n477"/>
   </struct>
   <struct type="nchunk" from="8933" to="8945">
      <feat name="graf:set" value="xces"/>
      <feat name="graf:id" value="n478"/>
   </struct>
   <struct type="nchunk" from="8960" to="8964">
      <feat name="graf:set" value="xces"/>
      <feat name="graf:id" value="n479"/>
   </struct>
   <struct type="nchunk" from="8977" to="8981">
      <feat name="graf:set" value="xces"/>
      <feat name="graf:id" value="n480"/>
   </struct>
   <struct type="nchunk" from="8987" to="8997">
      <feat name="graf:set" value="xces"/>
      <feat name="graf:id" value="n481"/>
   </struct>
   <struct type="nchunk" from="9012" to="9014">
      <feat name="graf:set" value="xces"/>
      <feat name="graf:id" value="n482"/>
   </struct>
   <struct type="nchunk" from="9029" to="9031">
      <feat name="graf:set" value="xces"/>
      <feat name="graf:id" value="n483"/>
   </struct>
   <struct type="nchunk" from="9040" to="9050">
      <feat name="graf:set" value="xces"/>
      <feat name="graf:id" value="n484"/>
   </struct>
   <struct type="nchunk" from="9055" to="9057">
      <feat name="graf:set" value="xces"/>
      <feat name="graf:id" value="n485"/>
   </struct>
   <struct type="nchunk" from="9076" to="9084">
      <feat name="graf:set" value="xces"/>
      <feat name="graf:id" value="n486"/>
   </struct>
   <struct type="nchunk" from="9089" to="9091">
      <feat name="graf:set" value="xces"/>
      <feat name="graf:id" value="n487"/>
   </struct>
   <struct type="nchunk" from="9107" to="9124">
      <feat name="graf:set" value="xces"/>
      <feat name="graf:id" value="n488"/>
   </struct>
   <struct type="nchunk" from="9137" to="9139">
      <feat name="graf:set" value="xces"/>
      <feat name="graf:id" value="n489"/>
   </struct>
   <struct type="nchunk" from="9144" to="9156">
      <feat name="graf:set" value="xces"/>
      <feat name="graf:id" value="n490"/>
   </struct>
   <struct type="nchunk" from="9174" to="9182">
      <feat name="graf:set" value="xces"/>
      <feat name="graf:id" value="n491"/>
   </struct>
   <struct type="nchunk" from="9184" to="9186">
      <feat name="graf:set" value="xces"/>
      <feat name="graf:id" value="n492"/>
   </struct>
   <struct type="nchunk" from="9191" to="9202">
      <feat name="graf:set" value="xces"/>
      <feat name="graf:id" value="n493"/>
   </struct>
   <struct type="nchunk" from="9230" to="9244">
      <feat name="graf:set" value="xces"/>
      <feat name="graf:id" value="n494"/>
   </struct>
   <struct type="nchunk" from="9263" to="9272">
      <feat name="graf:set" value="xces"/>
      <feat name="graf:id" value="n495"/>
   </struct>
   <struct type="nchunk" from="9290" to="9297">
      <feat name="graf:set" value="xces"/>
      <feat name="graf:id" value="n496"/>
   </struct>
   <struct type="nchunk" from="9309" to="9319">
      <feat name="graf:set" value="xces"/>
      <feat name="graf:id" value="n497"/>
   </struct>
   <struct type="nchunk" from="9324" to="9326">
      <feat name="graf:set" value="xces"/>
      <feat name="graf:id" value="n498"/>
   </struct>
   <struct type="nchunk" from="9337" to="9347">
      <feat name="graf:set" value="xces"/>
      <feat name="graf:id" value="n499"/>
   </struct>
   <struct type="nchunk" from="9357" to="9365">
      <feat name="graf:set" value="xces"/>
      <feat name="graf:id" value="n500"/>
   </struct>
   <struct type="nchunk" from="9370" to="9382">
      <feat name="graf:set" value="xces"/>
      <feat name="graf:id" value="n501"/>
   </struct>
   <struct type="nchunk" from="9400" to="9410">
      <feat name="graf:set" value="xces"/>
      <feat name="graf:id" value="n502"/>
   </struct>
   <struct type="nchunk" from="9414" to="9425">
      <feat name="graf:set" value="xces"/>
      <feat name="graf:id" value="n503"/>
   </struct>
   <struct type="nchunk" from="9435" to="9452">
      <feat name="graf:set" value="xces"/>
      <feat name="graf:id" value="n504"/>
   </struct>
   <struct type="nchunk" from="9460" to="9463">
      <feat name="graf:set" value="xces"/>
      <feat name="graf:id" value="n505"/>
   </struct>
   <struct type="nchunk" from="9468" to="9472">
      <feat name="graf:set" value="xces"/>
      <feat name="graf:id" value="n506"/>
   </struct>
   <struct type="nchunk" from="9482" to="9492">
      <feat name="graf:set" value="xces"/>
      <feat name="graf:id" value="n507"/>
   </struct>
   <struct type="nchunk" from="9497" to="9500">
      <feat name="graf:set" value="xces"/>
      <feat name="graf:id" value="n508"/>
   </struct>
   <struct type="nchunk" from="9510" to="9547">
      <feat name="graf:set" value="xces"/>
      <feat name="graf:id" value="n509"/>
   </struct>
   <struct type="nchunk" from="9563" to="9564">
      <feat name="graf:set" value="xces"/>
      <feat name="graf:id" value="n510"/>
   </struct>
   <struct type="nchunk" from="9569" to="9579">
      <feat name="graf:set" value="xces"/>
      <feat name="graf:id" value="n511"/>
   </struct>
   <struct type="nchunk" from="9581" to="9604">
      <feat name="graf:set" value="xces"/>
      <feat name="graf:id" value="n512"/>
   </struct>
   <struct type="nchunk" from="9632" to="9636">
      <feat name="graf:set" value="xces"/>
      <feat name="graf:id" value="n513"/>
   </struct>
   <struct type="nchunk" from="9651" to="9652">
      <feat name="graf:set" value="xces"/>
      <feat name="graf:id" value="n514"/>
   </struct>
   <struct type="nchunk" from="9659" to="9660">
      <feat name="graf:set" value="xces"/>
      <feat name="graf:id" value="n515"/>
   </struct>
   <struct type="nchunk" from="9674" to="9688">
      <feat name="graf:set" value="xces"/>
      <feat name="graf:id" value="n516"/>
   </struct>
   <struct type="nchunk" from="9694" to="9696">
      <feat name="graf:set" value="xces"/>
      <feat name="graf:id" value="n517"/>
   </struct>
   <struct type="nchunk" from="9705" to="9716">
      <feat name="graf:set" value="xces"/>
      <feat name="graf:id" value="n518"/>
   </struct>
   <struct type="nchunk" from="9731" to="9732">
      <feat name="graf:set" value="xces"/>
      <feat name="graf:id" value="n519"/>
   </struct>
   <struct type="nchunk" from="9737" to="9759">
      <feat name="graf:set" value="xces"/>
      <feat name="graf:id" value="n520"/>
   </struct>
   <struct type="nchunk" from="9765" to="9766">
      <feat name="graf:set" value="xces"/>
      <feat name="graf:id" value="n521"/>
   </struct>
   <struct type="nchunk" from="9787" to="9792">
      <feat name="graf:set" value="xces"/>
      <feat name="graf:id" value="n522"/>
   </struct>
   <struct type="nchunk" from="9806" to="9811">
      <feat name="graf:set" value="xces"/>
      <feat name="graf:id" value="n523"/>
   </struct>
   <struct type="nchunk" from="9826" to="9839">
      <feat name="graf:set" value="xces"/>
      <feat name="graf:id" value="n524"/>
   </struct>
   <struct type="nchunk" from="9840" to="9843">
      <feat name="graf:set" value="xces"/>
      <feat name="graf:id" value="n525"/>
   </struct>
   <struct type="nchunk" from="9849" to="9861">
      <feat name="graf:set" value="xces"/>
      <feat name="graf:id" value="n526"/>
   </struct>
   <struct type="nchunk" from="9872" to="9881">
      <feat name="graf:set" value="xces"/>
      <feat name="graf:id" value="n527"/>
   </struct>
   <struct type="nchunk" from="9886" to="9909">
      <feat name="graf:set" value="xces"/>
      <feat name="graf:id" value="n528"/>
   </struct>
   <struct type="nchunk" from="9919" to="9921">
      <feat name="graf:set" value="xces"/>
      <feat name="graf:id" value="n529"/>
   </struct>
   <struct type="nchunk" from="9926" to="9939">
      <feat name="graf:set" value="xces"/>
      <feat name="graf:id" value="n530"/>
   </struct>
   <struct type="nchunk" from="9945" to="9947">
      <feat name="graf:set" value="xces"/>
      <feat name="graf:id" value="n531"/>
   </struct>
   <struct type="nchunk" from="9959" to="9964">
      <feat name="graf:set" value="xces"/>
      <feat name="graf:id" value="n532"/>
   </struct>
   <struct type="nchunk" from="9968" to="9974">
      <feat name="graf:set" value="xces"/>
      <feat name="graf:id" value="n533"/>
   </struct>
   <struct type="nchunk" from="10002" to="10004">
      <feat name="graf:set" value="xces"/>
      <feat name="graf:id" value="n534"/>
   </struct>
   <struct type="nchunk" from="10016" to="10031">
      <feat name="graf:set" value="xces"/>
      <feat name="graf:id" value="n535"/>
   </struct>
   <struct type="nchunk" from="10036" to="10038">
      <feat name="graf:set" value="xces"/>
      <feat name="graf:id" value="n536"/>
   </struct>
   <struct type="nchunk" from="10060" to="10076">
      <feat name="graf:set" value="xces"/>
      <feat name="graf:id" value="n537"/>
   </struct>
   <struct type="nchunk" from="10092" to="10095">
      <feat name="graf:set" value="xces"/>
      <feat name="graf:id" value="n538"/>
   </struct>
   <struct type="nchunk" from="10099" to="10108">
      <feat name="graf:set" value="xces"/>
      <feat name="graf:id" value="n539"/>
   </struct>
   <struct type="nchunk" from="10110" to="10121">
      <feat name="graf:set" value="xces"/>
      <feat name="graf:id" value="n540"/>
   </struct>
   <struct type="nchunk" from="10123" to="10130">
      <feat name="graf:set" value="xces"/>
      <feat name="graf:id" value="n541"/>
   </struct>
   <struct type="nchunk" from="10135" to="10146">
      <feat name="graf:set" value="xces"/>
      <feat name="graf:id" value="n542"/>
   </struct>
   <struct type="nchunk" from="10152" to="10154">
      <feat name="graf:set" value="xces"/>
      <feat name="graf:id" value="n543"/>
   </struct>
   <struct type="nchunk" from="10166" to="10173">
      <feat name="graf:set" value="xces"/>
      <feat name="graf:id" value="n544"/>
   </struct>
   <struct type="nchunk" from="10177" to="10191">
      <feat name="graf:set" value="xces"/>
      <feat name="graf:id" value="n545"/>
   </struct>
   <struct type="nchunk" from="10220" to="10231">
      <feat name="graf:set" value="xces"/>
      <feat name="graf:id" value="n546"/>
   </struct>
   <struct type="nchunk" from="10305" to="10308">
      <feat name="graf:set" value="xces"/>
      <feat name="graf:id" value="n547"/>
   </struct>
   <struct type="nchunk" from="10356" to="10358">
      <feat name="graf:set" value="xces"/>
      <feat name="graf:id" value="n548"/>
   </struct>
   <struct type="nchunk" from="10368" to="10377">
      <feat name="graf:set" value="xces"/>
      <feat name="graf:id" value="n549"/>
   </struct>
   <struct type="nchunk" from="10381" to="10390">
      <feat name="graf:set" value="xces"/>
      <feat name="graf:id" value="n550"/>
   </struct>
   <struct type="nchunk" from="10403" to="10405">
      <feat name="graf:set" value="xces"/>
      <feat name="graf:id" value="n551"/>
   </struct>
   <struct type="nchunk" from="10414" to="10423">
      <feat name="graf:set" value="xces"/>
      <feat name="graf:id" value="n552"/>
   </struct>
   <struct type="nchunk" from="10424" to="10426">
      <feat name="graf:set" value="xces"/>
      <feat name="graf:id" value="n553"/>
   </struct>
   <struct type="nchunk" from="10439" to="10444">
      <feat name="graf:set" value="xces"/>
      <feat name="graf:id" value="n554"/>
   </struct>
   <struct type="nchunk" from="10454" to="10456">
      <feat name="graf:set" value="xces"/>
      <feat name="graf:id" value="n555"/>
   </struct>
   <struct type="nchunk" from="10478" to="10486">
      <feat name="graf:set" value="xces"/>
      <feat name="graf:id" value="n556"/>
   </struct>
   <struct type="nchunk" from="10490" to="10499">
      <feat name="graf:set" value="xces"/>
      <feat name="graf:id" value="n557"/>
   </struct>
   <struct type="nchunk" from="10504" to="10520">
      <feat name="graf:set" value="xces"/>
      <feat name="graf:id" value="n558"/>
   </struct>
   <struct type="nchunk" from="10526" to="10528">
      <feat name="graf:set" value="xces"/>
      <feat name="graf:id" value="n559"/>
   </struct>
   <struct type="nchunk" from="10541" to="10559">
      <feat name="graf:set" value="xces"/>
      <feat name="graf:id" value="n560"/>
   </struct>
   <struct type="nchunk" from="10565" to="10567">
      <feat name="graf:set" value="xces"/>
      <feat name="graf:id" value="n561"/>
   </struct>
   <struct type="nchunk" from="10581" to="10590">
      <feat name="graf:set" value="xces"/>
      <feat name="graf:id" value="n562"/>
   </struct>
   <struct type="nchunk" from="10595" to="10603">
      <feat name="graf:set" value="xces"/>
      <feat name="graf:id" value="n563"/>
   </struct>
   <struct type="nchunk" from="10614" to="10618">
      <feat name="graf:set" value="xces"/>
      <feat name="graf:id" value="n564"/>
   </struct>
   <struct type="nchunk" from="10628" to="10653">
      <feat name="graf:set" value="xces"/>
      <feat name="graf:id" value="n565"/>
   </struct>
   <struct type="nchunk" from="10659" to="10671">
      <feat name="graf:set" value="xces"/>
      <feat name="graf:id" value="n566"/>
   </struct>
   <struct type="nchunk" from="10695" to="10697">
      <feat name="graf:set" value="xces"/>
      <feat name="graf:id" value="n567"/>
   </struct>
   <struct type="nchunk" from="10706" to="10718">
      <feat name="graf:set" value="xces"/>
      <feat name="graf:id" value="n568"/>
   </struct>
   <struct type="nchunk" from="10723" to="10725">
      <feat name="graf:set" value="xces"/>
      <feat name="graf:id" value="n569"/>
   </struct>
   <struct type="nchunk" from="10737" to="10754">
      <feat name="graf:set" value="xces"/>
      <feat name="graf:id" value="n570"/>
   </struct>
   <struct type="nchunk" from="10759" to="10761">
      <feat name="graf:set" value="xces"/>
      <feat name="graf:id" value="n571"/>
   </struct>
   <struct type="nchunk" from="10774" to="10783">
      <feat name="graf:set" value="xces"/>
      <feat name="graf:id" value="n572"/>
   </struct>
   <struct type="nchunk" from="10798" to="10800">
      <feat name="graf:set" value="xces"/>
      <feat name="graf:id" value="n573"/>
   </struct>
   <struct type="nchunk" from="10805" to="10813">
      <feat name="graf:set" value="xces"/>
      <feat name="graf:id" value="n574"/>
   </struct>
   <struct type="nchunk" from="10829" to="10838">
      <feat name="graf:set" value="xces"/>
      <feat name="graf:id" value="n575"/>
   </struct>
   <struct type="nchunk" from="10843" to="10844">
      <feat name="graf:set" value="xces"/>
      <feat name="graf:id" value="n576"/>
   </struct>
   <struct type="nchunk" from="10865" to="10879">
      <feat name="graf:set" value="xces"/>
      <feat name="graf:id" value="n577"/>
   </struct>
   <struct type="nchunk" from="10892" to="10894">
      <feat name="graf:set" value="xces"/>
      <feat name="graf:id" value="n578"/>
   </struct>
   <struct type="nchunk" from="10907" to="10912">
      <feat name="graf:set" value="xces"/>
      <feat name="graf:id" value="n579"/>
   </struct>
   <struct type="nchunk" from="10922" to="10926">
      <feat name="graf:set" value="xces"/>
      <feat name="graf:id" value="n580"/>
   </struct>
   <struct type="nchunk" from="10937" to="10939">
      <feat name="graf:set" value="xces"/>
      <feat name="graf:id" value="n581"/>
   </struct>
   <struct type="nchunk" from="10957" to="10962">
      <feat name="graf:set" value="xces"/>
      <feat name="graf:id" value="n582"/>
   </struct>
   <struct type="nchunk" from="10976" to="10978">
      <feat name="graf:set" value="xces"/>
      <feat name="graf:id" value="n583"/>
   </struct>
   <struct type="nchunk" from="10986" to="11002">
      <feat name="graf:set" value="xces"/>
      <feat name="graf:id" value="n584"/>
   </struct>
   <struct type="nchunk" from="11007" to="11021">
      <feat name="graf:set" value="xces"/>
      <feat name="graf:id" value="n585"/>
   </struct>
   <struct type="nchunk" from="11027" to="11029">
      <feat name="graf:set" value="xces"/>
      <feat name="graf:id" value="n586"/>
   </struct>
   <struct type="nchunk" from="11034" to="11037">
      <feat name="graf:set" value="xces"/>
      <feat name="graf:id" value="n587"/>
   </struct>
   <struct type="nchunk" from="11042" to="11044">
      <feat name="graf:set" value="xces"/>
      <feat name="graf:id" value="n588"/>
   </struct>
   <struct type="nchunk" from="11069" to="11071">
      <feat name="graf:set" value="xces"/>
      <feat name="graf:id" value="n589"/>
   </struct>
   <struct type="nchunk" from="11082" to="11084">
      <feat name="graf:set" value="xces"/>
      <feat name="graf:id" value="n590"/>
   </struct>
   <struct type="nchunk" from="11094" to="11098">
      <feat name="graf:set" value="xces"/>
      <feat name="graf:id" value="n591"/>
   </struct>
   <struct type="nchunk" from="11099" to="11101">
      <feat name="graf:set" value="xces"/>
      <feat name="graf:id" value="n592"/>
   </struct>
   <struct type="nchunk" from="11140" to="11150">
      <feat name="graf:set" value="xces"/>
      <feat name="graf:id" value="n593"/>
   </struct>
   <struct type="nchunk" from="11151" to="11153">
      <feat name="graf:set" value="xces"/>
      <feat name="graf:id" value="n594"/>
   </struct>
   <struct type="nchunk" from="11183" to="11187">
      <feat name="graf:set" value="xces"/>
      <feat name="graf:id" value="n595"/>
   </struct>
   <struct type="nchunk" from="11192" to="11193">
      <feat name="graf:set" value="xces"/>
      <feat name="graf:id" value="n596"/>
   </struct>
   <struct type="nchunk" from="11200" to="11202">
      <feat name="graf:set" value="xces"/>
      <feat name="graf:id" value="n597"/>
   </struct>
   <struct type="nchunk" from="11213" to="11230">
      <feat name="graf:set" value="xces"/>
      <feat name="graf:id" value="n598"/>
   </struct>
   <struct type="nchunk" from="11236" to="11237">
      <feat name="graf:set" value="xces"/>
      <feat name="graf:id" value="n599"/>
   </struct>
   <struct type="nchunk" from="11257" to="11260">
      <feat name="graf:set" value="xces"/>
      <feat name="graf:id" value="n600"/>
   </struct>
   <struct type="nchunk" from="11271" to="11285">
      <feat name="graf:set" value="xces"/>
      <feat name="graf:id" value="n601"/>
   </struct>
   <struct type="nchunk" from="11292" to="11301">
      <feat name="graf:set" value="xces"/>
      <feat name="graf:id" value="n602"/>
   </struct>
   <struct type="nchunk" from="11305" to="11319">
      <feat name="graf:set" value="xces"/>
      <feat name="graf:id" value="n603"/>
   </struct>
   <struct type="nchunk" from="11320" to="11322">
      <feat name="graf:set" value="xces"/>
      <feat name="graf:id" value="n604"/>
   </struct>
   <struct type="nchunk" from="11325" to="11362">
      <feat name="graf:set" value="xces"/>
      <feat name="graf:id" value="n605"/>
   </struct>
   <struct type="nchunk" from="11364" to="11366">
      <feat name="graf:set" value="xces"/>
      <feat name="graf:id" value="n606"/>
   </struct>
   <struct type="nchunk" from="11377" to="11391">
      <feat name="graf:set" value="xces"/>
      <feat name="graf:id" value="n607"/>
   </struct>
   <struct type="nchunk" from="11396" to="11398">
      <feat name="graf:set" value="xces"/>
      <feat name="graf:id" value="n608"/>
   </struct>
   <struct type="nchunk" from="11457" to="11469">
      <feat name="graf:set" value="xces"/>
      <feat name="graf:id" value="n609"/>
   </struct>
   <struct type="nchunk" from="11483" to="11485">
      <feat name="graf:set" value="xces"/>
      <feat name="graf:id" value="n610"/>
   </struct>
   <struct type="nchunk" from="11493" to="11504">
      <feat name="graf:set" value="xces"/>
      <feat name="graf:id" value="n611"/>
   </struct>
   <struct type="nchunk" from="11509" to="11511">
      <feat name="graf:set" value="xces"/>
      <feat name="graf:id" value="n612"/>
   </struct>
   <struct type="nchunk" from="11522" to="11539">
      <feat name="graf:set" value="xces"/>
      <feat name="graf:id" value="n613"/>
   </struct>
   <struct type="nchunk" from="11544" to="11546">
      <feat name="graf:set" value="xces"/>
      <feat name="graf:id" value="n614"/>
   </struct>
   <struct type="nchunk" from="11553" to="11567">
      <feat name="graf:set" value="xces"/>
      <feat name="graf:id" value="n615"/>
   </struct>
   <struct type="nchunk" from="11572" to="11574">
      <feat name="graf:set" value="xces"/>
      <feat name="graf:id" value="n616"/>
   </struct>
   <struct type="nchunk" from="11586" to="11589">
      <feat name="graf:set" value="xces"/>
      <feat name="graf:id" value="n617"/>
   </struct>
   <struct type="nchunk" from="11613" to="11614">
      <feat name="graf:set" value="xces"/>
      <feat name="graf:id" value="n618"/>
   </struct>
   <struct type="nchunk" from="11641" to="11642">
      <feat name="graf:set" value="xces"/>
      <feat name="graf:id" value="n619"/>
   </struct>
   <struct type="nchunk" from="11658" to="11674">
      <feat name="graf:set" value="xces"/>
      <feat name="graf:id" value="n620"/>
   </struct>
   <struct type="nchunk" from="11676" to="11677">
      <feat name="graf:set" value="xces"/>
      <feat name="graf:id" value="n621"/>
   </struct>
   <struct type="nchunk" from="11689" to="11695">
      <feat name="graf:set" value="xces"/>
      <feat name="graf:id" value="n622"/>
   </struct>
   <struct type="nchunk" from="11705" to="11710">
      <feat name="graf:set" value="xces"/>
      <feat name="graf:id" value="n623"/>
   </struct>
   <struct type="nchunk" from="11721" to="11731">
      <feat name="graf:set" value="xces"/>
      <feat name="graf:id" value="n624"/>
   </struct>
   <struct type="nchunk" from="11735" to="11737">
      <feat name="graf:set" value="xces"/>
      <feat name="graf:id" value="n625"/>
   </struct>
   <struct type="nchunk" from="11752" to="11753">
      <feat name="graf:set" value="xces"/>
      <feat name="graf:id" value="n626"/>
   </struct>
   <struct type="nchunk" from="11768" to="11778">
      <feat name="graf:set" value="xces"/>
      <feat name="graf:id" value="n627"/>
   </struct>
   <struct type="nchunk" from="11788" to="11793">
      <feat name="graf:set" value="xces"/>
      <feat name="graf:id" value="n628"/>
   </struct>
   <struct type="nchunk" from="11797" to="11801">
      <feat name="graf:set" value="xces"/>
      <feat name="graf:id" value="n629"/>
   </struct>
   <struct type="nchunk" from="11847" to="11849">
      <feat name="graf:set" value="xces"/>
      <feat name="graf:id" value="n630"/>
   </struct>
   <struct type="nchunk" from="11852" to="11859">
      <feat name="graf:set" value="xces"/>
      <feat name="graf:id" value="n631"/>
   </struct>
   <struct type="nchunk" from="11865" to="11877">
      <feat name="graf:set" value="xces"/>
      <feat name="graf:id" value="n632"/>
   </struct>
   <struct type="nchunk" from="11891" to="11896">
      <feat name="graf:set" value="xces"/>
      <feat name="graf:id" value="n633"/>
   </struct>
   <struct type="nchunk" from="11902" to="11908">
      <feat name="graf:set" value="xces"/>
      <feat name="graf:id" value="n634"/>
   </struct>
   <struct type="nchunk" from="11914" to="11918">
      <feat name="graf:set" value="xces"/>
      <feat name="graf:id" value="n635"/>
   </struct>
   <struct type="nchunk" from="11922" to="11924">
      <feat name="graf:set" value="xces"/>
      <feat name="graf:id" value="n636"/>
   </struct>
   <struct type="nchunk" from="11935" to="11944">
      <feat name="graf:set" value="xces"/>
      <feat name="graf:id" value="n637"/>
   </struct>
   <struct type="nchunk" from="11948" to="11958">
      <feat name="graf:set" value="xces"/>
      <feat name="graf:id" value="n638"/>
   </struct>
   <struct type="nchunk" from="11959" to="11967">
      <feat name="graf:set" value="xces"/>
      <feat name="graf:id" value="n639"/>
   </struct>
   <struct type="nchunk" from="11968" to="11970">
      <feat name="graf:set" value="xces"/>
      <feat name="graf:id" value="n640"/>
   </struct>
   <struct type="nchunk" from="11981" to="11985">
      <feat name="graf:set" value="xces"/>
      <feat name="graf:id" value="n641"/>
   </struct>
   <struct type="nchunk" from="11989" to="12009">
      <feat name="graf:set" value="xces"/>
      <feat name="graf:id" value="n642"/>
   </struct>
   <struct type="nchunk" from="12020" to="12024">
      <feat name="graf:set" value="xces"/>
      <feat name="graf:id" value="n643"/>
   </struct>
   <struct type="nchunk" from="12034" to="12059">
      <feat name="graf:set" value="xces"/>
      <feat name="graf:id" value="n644"/>
   </struct>
   <struct type="nchunk" from="12094" to="12102">
      <feat name="graf:set" value="xces"/>
      <feat name="graf:id" value="n645"/>
   </struct>
   <struct type="nchunk" from="12106" to="12115">
      <feat name="graf:set" value="xces"/>
      <feat name="graf:id" value="n646"/>
   </struct>
   <struct type="nchunk" from="12130" to="12135">
      <feat name="graf:set" value="xces"/>
      <feat name="graf:id" value="n647"/>
   </struct>
   <struct type="nchunk" from="12140" to="12147">
      <feat name="graf:set" value="xces"/>
      <feat name="graf:id" value="n648"/>
   </struct>
   <struct type="nchunk" from="12151" to="12160">
      <feat name="graf:set" value="xces"/>
      <feat name="graf:id" value="n649"/>
   </struct>
   <struct type="nchunk" from="12161" to="12162">
      <feat name="graf:set" value="xces"/>
      <feat name="graf:id" value="n650"/>
   </struct>
   <struct type="nchunk" from="12178" to="12187">
      <feat name="graf:set" value="xces"/>
      <feat name="graf:id" value="n651"/>
   </struct>
   <struct type="nchunk" from="12191" to="12193">
      <feat name="graf:set" value="xces"/>
      <feat name="graf:id" value="n652"/>
   </struct>
   <struct type="nchunk" from="12199" to="12201">
      <feat name="graf:set" value="xces"/>
      <feat name="graf:id" value="n653"/>
   </struct>
   <struct type="nchunk" from="12209" to="12223">
      <feat name="graf:set" value="xces"/>
      <feat name="graf:id" value="n654"/>
   </struct>
   <struct type="nchunk" from="12229" to="12243">
      <feat name="graf:set" value="xces"/>
      <feat name="graf:id" value="n655"/>
   </struct>
   <struct type="nchunk" from="12247" to="12258">
      <feat name="graf:set" value="xces"/>
      <feat name="graf:id" value="n656"/>
   </struct>
   <struct type="nchunk" from="12260" to="12264">
      <feat name="graf:set" value="xces"/>
      <feat name="graf:id" value="n657"/>
   </struct>
   <struct type="nchunk" from="12281" to="12289">
      <feat name="graf:set" value="xces"/>
      <feat name="graf:id" value="n658"/>
   </struct>
   <struct type="nchunk" from="12304" to="12308">
      <feat name="graf:set" value="xces"/>
      <feat name="graf:id" value="n659"/>
   </struct>
   <struct type="nchunk" from="12322" to="12323">
      <feat name="graf:set" value="xces"/>
      <feat name="graf:id" value="n660"/>
   </struct>
   <struct type="nchunk" from="12339" to="12349">
      <feat name="graf:set" value="xces"/>
      <feat name="graf:id" value="n661"/>
   </struct>
   <struct type="nchunk" from="12351" to="12353">
      <feat name="graf:set" value="xces"/>
      <feat name="graf:id" value="n662"/>
   </struct>
   <struct type="nchunk" from="12363" to="12368">
      <feat name="graf:set" value="xces"/>
      <feat name="graf:id" value="n663"/>
   </struct>
   <struct type="nchunk" from="12372" to="12375">
      <feat name="graf:set" value="xces"/>
      <feat name="graf:id" value="n664"/>
   </struct>
   <struct type="nchunk" from="12390" to="12391">
      <feat name="graf:set" value="xces"/>
      <feat name="graf:id" value="n665"/>
   </struct>
   <struct type="nchunk" from="12409" to="12421">
      <feat name="graf:set" value="xces"/>
      <feat name="graf:id" value="n666"/>
   </struct>
   <struct type="nchunk" from="12431" to="12442">
      <feat name="graf:set" value="xces"/>
      <feat name="graf:id" value="n667"/>
   </struct>
   <struct type="nchunk" from="12448" to="12452">
      <feat name="graf:set" value="xces"/>
      <feat name="graf:id" value="n668"/>
   </struct>
   <struct type="nchunk" from="12465" to="12475">
      <feat name="graf:set" value="xces"/>
      <feat name="graf:id" value="n669"/>
   </struct>
   <struct type="nchunk" from="12481" to="12485">
      <feat name="graf:set" value="xces"/>
      <feat name="graf:id" value="n670"/>
   </struct>
   <struct type="nchunk" from="12522" to="12534">
      <feat name="graf:set" value="xces"/>
      <feat name="graf:id" value="n671"/>
   </struct>
</cesAna>