<?xml version="1.0" encoding="UTF-8"?>
<cesAna xmlns="http://www.xces.org/schema/2003" version="1.0">
   <struct type="VG" from="239" to="242">
      <feat name="voice" value="active"/>
      <feat name="tense" value="SimPre"/>
      <feat name="type" value="FVG"/>
   </struct>
   <struct type="VG" from="259" to="263">
      <feat name="voice" value="active"/>
      <feat name="tense" value="SimPas"/>
      <feat name="type" value="FVG"/>
   </struct>
   <struct type="VG" from="264" to="275">
      <feat name="voice" value="active"/>
      <feat name="tense" value="Inf"/>
      <feat name="type" value="NFVG"/>
   </struct>
   <struct type="VG" from="535" to="549">
      <feat name="voice" value="none"/>
      <feat name="tense" value="BeVBG"/>
      <feat name="type" value="MODAL"/>
   </struct>
   <struct type="VG" from="560" to="569">
      <feat name="voice" value="active"/>
      <feat name="tense" value="Inf"/>
      <feat name="type" value="NFVG"/>
   </struct>
   <struct type="VG" from="587" to="593">
      <feat name="voice" value="active"/>
      <feat name="tense" value="Pre"/>
      <feat name="type" value="PART"/>
   </struct>
   <struct type="VG" from="656" to="659">
      <feat name="voice" value="active"/>
      <feat name="tense" value="SimPre"/>
      <feat name="type" value="FVG"/>
   </struct>
   <struct type="VG" from="666" to="671">
      <feat name="voice" value="active"/>
      <feat name="tense" value="Pre"/>
      <feat name="type" value="PART"/>
   </struct>
   <struct type="VG" from="837" to="845">
      <feat name="voice" value="active"/>
      <feat name="tense" value="Inf"/>
      <feat name="type" value="NFVG"/>
   </struct>
   <struct type="VG" from="880" to="887">
      <feat name="voice" value="active"/>
      <feat name="tense" value="Inf"/>
      <feat name="type" value="NFVG"/>
   </struct>
   <struct type="VG" from="913" to="920">
      <feat name="voice" value="active"/>
      <feat name="tense" value="SimPre"/>
      <feat name="type" value="FVG"/>
   </struct>
   <struct type="VG" from="959" to="961">
      <feat name="voice" value="active"/>
      <feat name="tense" value="SimPre"/>
      <feat name="type" value="FVG"/>
   </struct>
   <struct type="VG" from="983" to="1003">
      <feat name="voice" value="active"/>
      <feat name="tense" value="Inf"/>
      <feat name="type" value="NFVG"/>
   </struct>
   <struct type="VG" from="1052" to="1057">
      <feat name="voice" value="active"/>
      <feat name="tense" value="Inf"/>
      <feat name="type" value="NFVG"/>
   </struct>
   <struct type="VG" from="1077" to="1082">
      <feat name="voice" value="active"/>
      <feat name="tense" value="Inf"/>
      <feat name="type" value="NFVG"/>
   </struct>
   <struct type="VG" from="1109" to="1115">
      <feat name="voice" value="active"/>
      <feat name="tense" value="Pre"/>
      <feat name="type" value="PART"/>
   </struct>
   <struct type="VG" from="1178" to="1184">
      <feat name="voice" value="none"/>
      <feat name="tense" value="Pas"/>
      <feat name="type" value="PART"/>
   </struct>
   <struct type="VG" from="1217" to="1225">
      <feat name="voice" value="active"/>
      <feat name="tense" value="Inf"/>
      <feat name="type" value="NFVG"/>
   </struct>
   <struct type="VG" from="1245" to="1247">
      <feat name="voice" value="active"/>
      <feat name="tense" value="SimPre"/>
      <feat name="type" value="FVG"/>
   </struct>
   <struct type="VG" from="1305" to="1308">
      <feat name="voice" value="active"/>
      <feat name="tense" value="SimPre"/>
      <feat name="type" value="FVG"/>
   </struct>
   <struct type="VG" from="1361" to="1363">
      <feat name="voice" value="active"/>
      <feat name="tense" value="SimPre"/>
      <feat name="type" value="FVG"/>
   </struct>
   <struct type="VG" from="1393" to="1405">
      <feat name="voice" value="active"/>
      <feat name="tense" value="Pre"/>
      <feat name="type" value="PART"/>
   </struct>
   <struct type="VG" from="1443" to="1453">
      <feat name="voice" value="active"/>
      <feat name="tense" value="Pre"/>
      <feat name="type" value="PART"/>
   </struct>
   <struct type="VG" from="1487" to="1494">
      <feat name="voice" value="active"/>
      <feat name="tense" value="Inf"/>
      <feat name="type" value="NFVG"/>
   </struct>
   <struct type="VG" from="1530" to="1536">
      <feat name="voice" value="active"/>
      <feat name="tense" value="SimPre"/>
      <feat name="type" value="FVG"/>
   </struct>
   <struct type="VG" from="1639" to="1648">
      <feat name="voice" value="active"/>
      <feat name="tense" value="SimPre"/>
      <feat name="type" value="FVG"/>
   </struct>
   <struct type="VG" from="1716" to="1723">
      <feat name="voice" value="active"/>
      <feat name="tense" value="SimPre"/>
      <feat name="type" value="FVG"/>
   </struct>
   <struct type="VG" from="1799" to="1806">
      <feat name="voice" value="active"/>
      <feat name="tense" value="SimPas"/>
      <feat name="type" value="FVG"/>
   </struct>
   <struct type="VG" from="1818" to="1829">
      <feat name="voice" value="none"/>
      <feat name="tense" value="Pas"/>
      <feat name="type" value="PART"/>
   </struct>
   <struct type="VG" from="1982" to="1987">
      <feat name="voice" value="none"/>
      <feat name="tense" value="Pas"/>
      <feat name="type" value="PART"/>
   </struct>
   <struct type="VG" from="2031" to="2037">
      <feat name="voice" value="active"/>
      <feat name="tense" value="SimPas"/>
      <feat name="type" value="FVG"/>
   </struct>
   <struct type="VG" from="2106" to="2111">
      <feat name="voice" value="active"/>
      <feat name="tense" value="SimPas"/>
      <feat name="type" value="FVG"/>
   </struct>
   <struct type="VG" from="2149" to="2159">
      <feat name="voice" value="active"/>
      <feat name="tense" value="Inf"/>
      <feat name="type" value="NFVG"/>
   </struct>
   <struct type="VG" from="2186" to="2193">
      <feat name="voice" value="none"/>
      <feat name="tense" value="Pas"/>
      <feat name="type" value="PART"/>
   </struct>
   <struct type="VG" from="2198" to="2209">
      <feat name="voice" value="none"/>
      <feat name="tense" value="Pas"/>
      <feat name="type" value="PART"/>
   </struct>
   <struct type="VG" from="2236" to="2244">
      <feat name="voice" value="active"/>
      <feat name="tense" value="Pre"/>
      <feat name="type" value="PART"/>
   </struct>
   <struct type="VG" from="2316" to="2324">
      <feat name="voice" value="active"/>
      <feat name="tense" value="SimPas"/>
      <feat name="type" value="FVG"/>
   </struct>
   <struct type="VG" from="2504" to="2512">
      <feat name="voice" value="active"/>
      <feat name="tense" value="SimPas"/>
      <feat name="type" value="FVG"/>
   </struct>
   <struct type="VG" from="2544" to="2552">
      <feat name="voice" value="active"/>
      <feat name="tense" value="Inf"/>
      <feat name="type" value="NFVG"/>
   </struct>
   <struct type="VG" from="2635" to="2641">
      <feat name="voice" value="active"/>
      <feat name="tense" value="SimPre"/>
      <feat name="type" value="FVG"/>
   </struct>
   <struct type="VG" from="2774" to="2779">
      <feat name="voice" value="active"/>
      <feat name="tense" value="SimPre"/>
      <feat name="type" value="FVG"/>
   </struct>
   <struct type="VG" from="2801" to="2807">
      <feat name="voice" value="active"/>
      <feat name="tense" value="Inf"/>
      <feat name="type" value="NFVG"/>
   </struct>
   <struct type="VG" from="2870" to="2872">
      <feat name="voice" value="active"/>
      <feat name="tense" value="SimPre"/>
      <feat name="type" value="FVG"/>
   </struct>
   <struct type="VG" from="2903" to="2906">
      <feat name="voice" value="active"/>
      <feat name="tense" value="Inf"/>
      <feat name="type" value="NFVG"/>
   </struct>
   <struct type="VG" from="2961" to="2969">
      <feat name="voice" value="none"/>
      <feat name="tense" value="Pas"/>
      <feat name="type" value="PART"/>
   </struct>
   <struct type="VG" from="2970" to="2983">
      <feat name="voice" value="active"/>
      <feat name="tense" value="Inf"/>
      <feat name="type" value="NFVG"/>
   </struct>
   <struct type="VG" from="3075" to="3081">
      <feat name="voice" value="active"/>
      <feat name="tense" value="Inf"/>
      <feat name="type" value="NFVG"/>
   </struct>
   <struct type="VG" from="3153" to="3155">
      <feat name="voice" value="active"/>
      <feat name="tense" value="SimPre"/>
      <feat name="type" value="FVG"/>
   </struct>
   <struct type="VG" from="3178" to="3182">
      <feat name="voice" value="active"/>
      <feat name="tense" value="SimPre"/>
      <feat name="type" value="FVG"/>
   </struct>
   <struct type="VG" from="3233" to="3236">
      <feat name="voice" value="active"/>
      <feat name="tense" value="SimPre"/>
      <feat name="type" value="FVG"/>
   </struct>
   <struct type="VG" from="3245" to="3247">
      <feat name="voice" value="active"/>
      <feat name="tense" value="SimPre"/>
      <feat name="type" value="FVG"/>
   </struct>
   <struct type="VG" from="3252" to="3258">
      <feat name="voice" value="active"/>
      <feat name="tense" value="Inf"/>
      <feat name="type" value="NFVG"/>
   </struct>
   <struct type="VG" from="3301" to="3309">
      <feat name="voice" value="none"/>
      <feat name="tense" value="Pas"/>
      <feat name="type" value="PART"/>
   </struct>
   <struct type="VG" from="3358" to="3365">
      <feat name="voice" value="active"/>
      <feat name="tense" value="SimPre"/>
      <feat name="type" value="FVG"/>
   </struct>
   <struct type="VG" from="3392" to="3401">
      <feat name="voice" value="none"/>
      <feat name="tense" value="none"/>
      <feat name="type" value="MODAL"/>
   </struct>
   <struct type="VG" from="3402" to="3407">
      <feat name="voice" value="active"/>
      <feat name="tense" value="Pre"/>
      <feat name="type" value="PART"/>
   </struct>
   <struct type="VG" from="3423" to="3427">
      <feat name="voice" value="active"/>
      <feat name="tense" value="SimPre"/>
      <feat name="type" value="FVG"/>
   </struct>
   <struct type="VG" from="3520" to="3524">
      <feat name="voice" value="active"/>
      <feat name="tense" value="SimPre"/>
      <feat name="type" value="FVG"/>
   </struct>
   <struct type="VG" from="3525" to="3535">
      <feat name="voice" value="none"/>
      <feat name="tense" value="none"/>
      <feat name="type" value="MODAL"/>
   </struct>
   <struct type="VG" from="3582" to="3585">
      <feat name="voice" value="active"/>
      <feat name="tense" value="SimPre"/>
      <feat name="type" value="FVG"/>
   </struct>
   <struct type="VG" from="3628" to="3636">
      <feat name="voice" value="active"/>
      <feat name="tense" value="Pre"/>
      <feat name="type" value="PART"/>
   </struct>
   <struct type="VG" from="3684" to="3695">
      <feat name="voice" value="active"/>
      <feat name="tense" value="Pre"/>
      <feat name="type" value="PART"/>
   </struct>
   <struct type="VG" from="3741" to="3754">
      <feat name="voice" value="active"/>
      <feat name="tense" value="SimFut"/>
      <feat name="type" value="FVG"/>
   </struct>
   <struct type="VG" from="3759" to="3762">
      <feat name="voice" value="active"/>
      <feat name="tense" value="Inf"/>
      <feat name="type" value="NFVG"/>
   </struct>
   <struct type="VG" from="4073" to="4081">
      <feat name="voice" value="active"/>
      <feat name="tense" value="Pre"/>
      <feat name="type" value="PART"/>
   </struct>
   <struct type="VG" from="4152" to="4159">
      <feat name="voice" value="active"/>
      <feat name="tense" value="Pre"/>
      <feat name="type" value="PART"/>
   </struct>
   <struct type="VG" from="4180" to="4191">
      <feat name="voice" value="active"/>
      <feat name="tense" value="Pre"/>
      <feat name="type" value="PART"/>
   </struct>
   <struct type="VG" from="4201" to="4207">
      <feat name="voice" value="active"/>
      <feat name="tense" value="Inf"/>
      <feat name="type" value="NFVG"/>
   </struct>
   <struct type="VG" from="4208" to="4213">
      <feat name="voice" value="active"/>
      <feat name="tense" value="SimPre"/>
      <feat name="type" value="FVG"/>
   </struct>
   <struct type="VG" from="4257" to="4262">
      <feat name="voice" value="active"/>
      <feat name="tense" value="SimPre"/>
      <feat name="type" value="FVG"/>
   </struct>
   <struct type="VG" from="4284" to="4293">
      <feat name="voice" value="none"/>
      <feat name="tense" value="Pas"/>
      <feat name="type" value="PART"/>
   </struct>
   <struct type="VG" from="4341" to="4352">
      <feat name="type" value="FVG"/>
      <feat name="tense" value="SimPre"/>
      <feat name="voice" value="active"/>
      <feat name="neg" value="yes"/>
   </struct>
   <struct type="VG" from="4353" to="4363">
      <feat name="voice" value="active"/>
      <feat name="tense" value="Inf"/>
      <feat name="type" value="NFVG"/>
   </struct>
   <struct type="VG" from="4428" to="4434">
      <feat name="voice" value="active"/>
      <feat name="tense" value="Inf"/>
      <feat name="type" value="NFVG"/>
   </struct>
   <struct type="VG" from="4517" to="4523">
      <feat name="voice" value="active"/>
      <feat name="tense" value="Inf"/>
      <feat name="type" value="NFVG"/>
   </struct>
   <struct type="VG" from="4524" to="4536">
      <feat name="type" value="FVG"/>
      <feat name="tense" value="SimPre"/>
      <feat name="voice" value="active"/>
      <feat name="neg" value="yes"/>
   </struct>
   <struct type="VG" from="4568" to="4571">
      <feat name="voice" value="active"/>
      <feat name="tense" value="SimPre"/>
      <feat name="type" value="FVG"/>
   </struct>
   <struct type="VG" from="4579" to="4590">
      <feat name="voice" value="active"/>
      <feat name="tense" value="Inf"/>
      <feat name="type" value="NFVG"/>
   </struct>
   <struct type="VG" from="4598" to="4602">
      <feat name="voice" value="active"/>
      <feat name="tense" value="SimPas"/>
      <feat name="type" value="FVG"/>
   </struct>
   <struct type="VG" from="4623" to="4627">
      <feat name="voice" value="active"/>
      <feat name="tense" value="Inf"/>
      <feat name="type" value="NFVG"/>
   </struct>
   <struct type="VG" from="4646" to="4650">
      <feat name="voice" value="active"/>
      <feat name="tense" value="SimPre"/>
      <feat name="type" value="FVG"/>
   </struct>
   <struct type="VG" from="4654" to="4662">
      <feat name="voice" value="active"/>
      <feat name="tense" value="SimFut"/>
      <feat name="type" value="FVG"/>
   </struct>
   <struct type="VG" from="4745" to="4756">
      <feat name="voice" value="active"/>
      <feat name="tense" value="Pre"/>
      <feat name="type" value="PART"/>
   </struct>
   <struct type="VG" from="4766" to="4772">
      <feat name="voice" value="active"/>
      <feat name="tense" value="Inf"/>
      <feat name="type" value="NFVG"/>
   </struct>
   <struct type="VG" from="4773" to="4778">
      <feat name="voice" value="active"/>
      <feat name="tense" value="SimPre"/>
      <feat name="type" value="FVG"/>
   </struct>
   <struct type="VG" from="4814" to="4825">
      <feat name="voice" value="active"/>
      <feat name="tense" value="Pre"/>
      <feat name="type" value="PART"/>
   </struct>
   <struct type="VG" from="4835" to="4841">
      <feat name="voice" value="active"/>
      <feat name="tense" value="Inf"/>
      <feat name="type" value="NFVG"/>
   </struct>
   <struct type="VG" from="4842" to="4847">
      <feat name="voice" value="active"/>
      <feat name="tense" value="SimPre"/>
      <feat name="type" value="FVG"/>
   </struct>
</cesAna>