<?xml version="1.0" encoding="UTF-8"?>
<cesAna xmlns="http://www.xces.org/schema/2003" version="null">
   <struct type="Clause" from="86" to="117">
      <feat name="ID" value="C1"/>
   </struct>
   <struct type="MARKER" from="86" to="88">
      <feat name="CONNECT" value="expect"/>
      <feat name="TYPE" value="ext"/>
      <feat name="NUC" value="_SN"/>
      <feat name="ID" value="m1"/>
   </struct>
   <struct type="Clause" from="167" to="193">
      <feat name="ID" value="C2"/>
   </struct>
   <struct type="MARKER" from="167" to="171">
      <feat name="NUC" value="N_N"/>
      <feat name="ID" value="m2"/>
      <feat name="CONNECT" value="fulfil"/>
      <feat name="TYPE" value="ext"/>
   </struct>
   <struct type="Clause" from="195" to="242">
      <feat name="ID" value="C3"/>
   </struct>
   <struct type="Clause" from="243" to="292">
      <feat name="ID" value="C4"/>
   </struct>
   <struct type="Clause" from="294" to="345">
      <feat name="ID" value="C5"/>
   </struct>
   <struct type="Clause" from="389" to="447">
      <feat name="ID" value="C6"/>
   </struct>
   <struct type="MARKER" from="389" to="391">
      <feat name="ID" value="m3"/>
      <feat name="NUC" value="_SN"/>
   </struct>
   <struct type="Clause" from="448" to="486">
      <feat name="ID" value="C7"/>
   </struct>
   <struct type="Clause" from="487" to="559">
      <feat name="ID" value="C8"/>
   </struct>
   <struct type="MARKER" from="487" to="489">
      <feat name="NUC" value="N_N"/>
      <feat name="ID" value="m4"/>
   </struct>
   <struct type="Clause" from="561" to="656">
      <feat name="ID" value="C9"/>
   </struct>
</cesAna>